{"took":9,"timed_out":false,"_shards":{"total":1,"successful":1,"skipped":0,"failed":0},"hits":{"total":{"value":367,"relation":"eq"},"max_score":null,"hits":[{"_index":"daily_temperature","_type":"_doc","_id":"cEunPnQBWtRdb_i9yprP","_score":null,"_source":{"station_id":"c24m124e03","date":"01-01-2016","t_min":9.1,"t_max":17.5,"t_avg":13.3,"week_number":1,"month":1},"sort":[1451606400000]},{"_index":"daily_temperature","_type":"_doc","_id":"oUunPnQBWtRdb_i9ypr8","_score":null,"_source":{"station_id":"c24m124e03","date":"02-01-2016","t_min":7.3,"t_max":12.6,"t_avg":9.9,"week_number":1,"month":1},"sort":[1451692800000]},{"_index":"daily_temperature","_type":"_doc","_id":"hEunPnQBWtRdb_i9yprb","_score":null,"_source":{"station_id":"c24m124e03","date":"03-01-2016","t_min":6.3,"t_max":13.9,"t_avg":10.1,"week_number":1,"month":1},"sort":[1451779200000]},{"_index":"daily_temperature","_type":"_doc","_id":"vEunPnQBWtRdb_i9y5oK","_score":null,"_source":{"station_id":"c24m124e03","date":"04-01-2016","t_min":13.2,"t_max":18.3,"t_avg":15.8,"week_number":1,"month":1},"sort":[1451865600000]},{"_index":"daily_temperature","_type":"_doc","_id":"xkunPnQBWtRdb_i9y5oN","_score":null,"_source":{"station_id":"c24m124e03","date":"05-01-2016","t_min":5.2,"t_max":14.5,"t_avg":9.8,"week_number":1,"month":1},"sort":[1451952000000]},{"_index":"daily_temperature","_type":"_doc","_id":"iEunPnQBWtRdb_i9yprc","_score":null,"_source":{"station_id":"c24m124e03","date":"06-01-2016","t_min":3,"t_max":8.6,"t_avg":5.8,"week_number":1,"month":1},"sort":[1452038400000]},{"_index":"daily_temperature","_type":"_doc","_id":"ZEunPnQBWtRdb_i9yprM","_score":null,"_source":{"station_id":"c24m124e03","date":"07-01-2016","t_min":7.7,"t_max":16.4,"t_avg":12.1,"week_number":1,"month":1},"sort":[1452124800000]},{"_index":"daily_temperature","_type":"_doc","_id":"uUunPnQBWtRdb_i9y5oJ","_score":null,"_source":{"station_id":"c24m124e03","date":"08-01-2016","t_min":7.6,"t_max":18.7,"t_avg":13.2,"week_number":2,"month":1},"sort":[1452211200000]},{"_index":"daily_temperature","_type":"_doc","_id":"gkunPnQBWtRdb_i9yprY","_score":null,"_source":{"station_id":"c24m124e03","date":"09-01-2016","t_min":10.1,"t_max":16.6,"t_avg":13.3,"week_number":2,"month":1},"sort":[1452297600000]},{"_index":"daily_temperature","_type":"_doc","_id":"WkunPnQBWtRdb_i9yprG","_score":null,"_source":{"station_id":"c24m124e03","date":"10-01-2016","t_min":9.2,"t_max":15.3,"t_avg":12.2,"week_number":2,"month":1},"sort":[1452384000000]},{"_index":"daily_temperature","_type":"_doc","_id":"WEunPnQBWtRdb_i9yprG","_score":null,"_source":{"station_id":"c24m124e03","date":"11-01-2016","t_min":8.3,"t_max":15.6,"t_avg":11.9,"week_number":2,"month":1},"sort":[1452470400000]},{"_index":"daily_temperature","_type":"_doc","_id":"sEunPnQBWtRdb_i9y5oF","_score":null,"_source":{"station_id":"c24m124e03","date":"12-01-2016","t_min":4.7,"t_max":10.2,"t_avg":7.5,"week_number":2,"month":1},"sort":[1452556800000]},{"_index":"daily_temperature","_type":"_doc","_id":"tEunPnQBWtRdb_i9y5oG","_score":null,"_source":{"station_id":"c24m124e03","date":"13-01-2016","t_min":0.2,"t_max":12.4,"t_avg":6.3,"week_number":2,"month":1},"sort":[1452643200000]},{"_index":"daily_temperature","_type":"_doc","_id":"UkunPnQBWtRdb_i9yprC","_score":null,"_source":{"station_id":"c24m124e03","date":"14-01-2016","t_min":2.9,"t_max":15,"t_avg":8.9,"week_number":2,"month":1},"sort":[1452729600000]},{"_index":"daily_temperature","_type":"_doc","_id":"eUunPnQBWtRdb_i9yprV","_score":null,"_source":{"station_id":"c24m124e03","date":"15-01-2016","t_min":3.7,"t_max":10.2,"t_avg":7,"week_number":3,"month":1},"sort":[1452816000000]},{"_index":"daily_temperature","_type":"_doc","_id":"dkunPnQBWtRdb_i9yprT","_score":null,"_source":{"station_id":"c24m124e03","date":"16-01-2016","t_min":0.2,"t_max":8.3,"t_avg":4.2,"week_number":3,"month":1},"sort":[1452902400000]},{"_index":"daily_temperature","_type":"_doc","_id":"nEunPnQBWtRdb_i9ypr5","_score":null,"_source":{"station_id":"c24m124e03","date":"17-01-2016","t_min":-3.3,"t_max":12.6,"t_avg":4.7,"week_number":3,"month":1},"sort":[1452988800000]},{"_index":"daily_temperature","_type":"_doc","_id":"S0unPnQBWtRdb_i9ypq_","_score":null,"_source":{"station_id":"c24m124e03","date":"18-01-2016","t_min":5.9,"t_max":13.2,"t_avg":9.6,"week_number":3,"month":1},"sort":[1453075200000]},{"_index":"daily_temperature","_type":"_doc","_id":"VUunPnQBWtRdb_i9yprC","_score":null,"_source":{"station_id":"c24m124e03","date":"19-01-2016","t_min":3.2,"t_max":11.8,"t_avg":7.5,"week_number":3,"month":1},"sort":[1453161600000]},{"_index":"daily_temperature","_type":"_doc","_id":"f0unPnQBWtRdb_i9yprW","_score":null,"_source":{"station_id":"c24m124e03","date":"20-01-2016","t_min":3.4,"t_max":12.9,"t_avg":8.2,"week_number":3,"month":1},"sort":[1453248000000]},{"_index":"daily_temperature","_type":"_doc","_id":"r0unPnQBWtRdb_i9y5oE","_score":null,"_source":{"station_id":"c24m124e03","date":"21-01-2016","t_min":2.3,"t_max":12.4,"t_avg":7.3,"week_number":3,"month":1},"sort":[1453334400000]},{"_index":"daily_temperature","_type":"_doc","_id":"iUunPnQBWtRdb_i9yprc","_score":null,"_source":{"station_id":"c24m124e03","date":"22-01-2016","t_min":6.6,"t_max":13.4,"t_avg":10,"week_number":4,"month":1},"sort":[1453420800000]},{"_index":"daily_temperature","_type":"_doc","_id":"bEunPnQBWtRdb_i9yprN","_score":null,"_source":{"station_id":"c24m124e03","date":"23-01-2016","t_min":6.1,"t_max":16.6,"t_avg":11.3,"week_number":4,"month":1},"sort":[1453507200000]},{"_index":"daily_temperature","_type":"_doc","_id":"jEunPnQBWtRdb_i9yprc","_score":null,"_source":{"station_id":"c24m124e03","date":"24-01-2016","t_min":5.9,"t_max":16.1,"t_avg":11,"week_number":4,"month":1},"sort":[1453593600000]},{"_index":"daily_temperature","_type":"_doc","_id":"0UunPnQBWtRdb_i9y5oP","_score":null,"_source":{"station_id":"c24m124e03","date":"25-01-2016","t_min":4.2,"t_max":19.2,"t_avg":11.7,"week_number":4,"month":1},"sort":[1453680000000]},{"_index":"daily_temperature","_type":"_doc","_id":"gEunPnQBWtRdb_i9yprX","_score":null,"_source":{"station_id":"c24m124e03","date":"26-01-2016","t_min":5.7,"t_max":11.7,"t_avg":8.7,"week_number":4,"month":1},"sort":[1453766400000]},{"_index":"daily_temperature","_type":"_doc","_id":"o0unPnQBWtRdb_i9ypr-","_score":null,"_source":{"station_id":"c24m124e03","date":"27-01-2016","t_min":5.2,"t_max":13.7,"t_avg":9.4,"week_number":4,"month":1},"sort":[1453852800000]},{"_index":"daily_temperature","_type":"_doc","_id":"YkunPnQBWtRdb_i9yprL","_score":null,"_source":{"station_id":"c24m124e03","date":"28-01-2016","t_min":2.4,"t_max":15.1,"t_avg":8.8,"week_number":4,"month":1},"sort":[1453939200000]},{"_index":"daily_temperature","_type":"_doc","_id":"q0unPnQBWtRdb_i9y5oD","_score":null,"_source":{"station_id":"c24m124e03","date":"29-01-2016","t_min":7.3,"t_max":8.8,"t_avg":8.1,"week_number":5,"month":1},"sort":[1454025600000]},{"_index":"daily_temperature","_type":"_doc","_id":"yUunPnQBWtRdb_i9y5oO","_score":null,"_source":{"station_id":"c24m124e03","date":"30-01-2016","t_min":7.5,"t_max":14.9,"t_avg":11.2,"week_number":5,"month":1},"sort":[1454112000000]},{"_index":"daily_temperature","_type":"_doc","_id":"dEunPnQBWtRdb_i9yprS","_score":null,"_source":{"station_id":"c24m124e03","date":"31-01-2016","t_min":6.7,"t_max":17.9,"t_avg":12.3,"week_number":5,"month":1},"sort":[1454198400000]},{"_index":"daily_temperature","_type":"_doc","_id":"hkunPnQBWtRdb_i9xZlr","_score":null,"_source":{"station_id":"c24m124e03","date":"01-02-2016","t_min":4.4,"t_max":18.3,"t_avg":11.3,"week_number":5,"month":2},"sort":[1454284800000]},{"_index":"daily_temperature","_type":"_doc","_id":"dEunPnQBWtRdb_i9xZlW","_score":null,"_source":{"station_id":"c24m124e03","date":"02-02-2016","t_min":4.3,"t_max":18.6,"t_avg":11.4,"week_number":5,"month":2},"sort":[1454371200000]},{"_index":"daily_temperature","_type":"_doc","_id":"hUunPnQBWtRdb_i9xZlr","_score":null,"_source":{"station_id":"c24m124e03","date":"03-02-2016","t_min":5.3,"t_max":15,"t_avg":10.2,"week_number":5,"month":2},"sort":[1454457600000]},{"_index":"daily_temperature","_type":"_doc","_id":"kEunPnQBWtRdb_i9xZl3","_score":null,"_source":{"station_id":"c24m124e03","date":"04-02-2016","t_min":1.4,"t_max":12.7,"t_avg":7,"week_number":5,"month":2},"sort":[1454544000000]},{"_index":"daily_temperature","_type":"_doc","_id":"i0unPnQBWtRdb_i9xZl2","_score":null,"_source":{"station_id":"c24m124e03","date":"05-02-2016","t_min":1.8,"t_max":12.7,"t_avg":7.2,"week_number":6,"month":2},"sort":[1454630400000]},{"_index":"daily_temperature","_type":"_doc","_id":"cEunPnQBWtRdb_i9xZlS","_score":null,"_source":{"station_id":"c24m124e03","date":"06-02-2016","t_min":3.1,"t_max":17.7,"t_avg":10.4,"week_number":6,"month":2},"sort":[1454716800000]},{"_index":"daily_temperature","_type":"_doc","_id":"U0unPnQBWtRdb_i9xZkw","_score":null,"_source":{"station_id":"c24m124e03","date":"07-02-2016","t_min":5.3,"t_max":12.7,"t_avg":9,"week_number":6,"month":2},"sort":[1454803200000]},{"_index":"daily_temperature","_type":"_doc","_id":"XkunPnQBWtRdb_i9xZk5","_score":null,"_source":{"station_id":"c24m124e03","date":"08-02-2016","t_min":7.8,"t_max":12.9,"t_avg":10.3,"week_number":6,"month":2},"sort":[1454889600000]},{"_index":"daily_temperature","_type":"_doc","_id":"n0unPnQBWtRdb_i9xZmM","_score":null,"_source":{"station_id":"c24m124e03","date":"09-02-2016","t_min":8.1,"t_max":15.1,"t_avg":11.6,"week_number":6,"month":2},"sort":[1454976000000]},{"_index":"daily_temperature","_type":"_doc","_id":"mEunPnQBWtRdb_i9xZl7","_score":null,"_source":{"station_id":"c24m124e03","date":"10-02-2016","t_min":9.9,"t_max":16.8,"t_avg":13.3,"week_number":6,"month":2},"sort":[1455062400000]},{"_index":"daily_temperature","_type":"_doc","_id":"eEunPnQBWtRdb_i9xZlf","_score":null,"_source":{"station_id":"c24m124e03","date":"11-02-2016","t_min":11.9,"t_max":17.6,"t_avg":14.8,"week_number":6,"month":2},"sort":[1455148800000]},{"_index":"daily_temperature","_type":"_doc","_id":"X0unPnQBWtRdb_i9xZk5","_score":null,"_source":{"station_id":"c24m124e03","date":"12-02-2016","t_min":10.4,"t_max":16.7,"t_avg":13.6,"week_number":7,"month":2},"sort":[1455235200000]},{"_index":"daily_temperature","_type":"_doc","_id":"l0unPnQBWtRdb_i9xZl7","_score":null,"_source":{"station_id":"c24m124e03","date":"13-02-2016","t_min":14.3,"t_max":17.3,"t_avg":15.8,"week_number":7,"month":2},"sort":[1455321600000]},{"_index":"daily_temperature","_type":"_doc","_id":"YEunPnQBWtRdb_i9xZk_","_score":null,"_source":{"station_id":"c24m124e03","date":"14-02-2016","t_min":3.8,"t_max":15.6,"t_avg":9.7,"week_number":7,"month":2},"sort":[1455408000000]},{"_index":"daily_temperature","_type":"_doc","_id":"kkunPnQBWtRdb_i9xZl5","_score":null,"_source":{"station_id":"c24m124e03","date":"15-02-2016","t_min":2.9,"t_max":10.4,"t_avg":6.7,"week_number":7,"month":2},"sort":[1455494400000]},{"_index":"daily_temperature","_type":"_doc","_id":"W0unPnQBWtRdb_i9xZk2","_score":null,"_source":{"station_id":"c24m124e03","date":"16-02-2016","t_min":-2.4,"t_max":9.1,"t_avg":3.4,"week_number":7,"month":2},"sort":[1455580800000]},{"_index":"daily_temperature","_type":"_doc","_id":"iUunPnQBWtRdb_i9xZlr","_score":null,"_source":{"station_id":"c24m124e03","date":"17-02-2016","t_min":-2.7,"t_max":9.4,"t_avg":3.4,"week_number":7,"month":2},"sort":[1455667200000]},{"_index":"daily_temperature","_type":"_doc","_id":"gkunPnQBWtRdb_i9xZlq","_score":null,"_source":{"station_id":"c24m124e03","date":"18-02-2016","t_min":3.8,"t_max":9.7,"t_avg":6.8,"week_number":7,"month":2},"sort":[1455753600000]},{"_index":"daily_temperature","_type":"_doc","_id":"g0unPnQBWtRdb_i9xZlq","_score":null,"_source":{"station_id":"c24m124e03","date":"19-02-2016","t_min":2.3,"t_max":8.9,"t_avg":5.6,"week_number":8,"month":2},"sort":[1455840000000]},{"_index":"daily_temperature","_type":"_doc","_id":"lUunPnQBWtRdb_i9xZl6","_score":null,"_source":{"station_id":"c24m124e03","date":"20-02-2016","t_min":2.2,"t_max":10.8,"t_avg":6.5,"week_number":8,"month":2},"sort":[1455926400000]},{"_index":"daily_temperature","_type":"_doc","_id":"kUunPnQBWtRdb_i9xZl3","_score":null,"_source":{"station_id":"c24m124e03","date":"21-02-2016","t_min":4.5,"t_max":14.1,"t_avg":9.3,"week_number":8,"month":2},"sort":[1456012800000]},{"_index":"daily_temperature","_type":"_doc","_id":"eUunPnQBWtRdb_i9xZlf","_score":null,"_source":{"station_id":"c24m124e03","date":"22-02-2016","t_min":6,"t_max":18.3,"t_avg":12.2,"week_number":8,"month":2},"sort":[1456099200000]},{"_index":"daily_temperature","_type":"_doc","_id":"Z0unPnQBWtRdb_i9xZlI","_score":null,"_source":{"station_id":"c24m124e03","date":"23-02-2016","t_min":5.2,"t_max":15.7,"t_avg":10.4,"week_number":8,"month":2},"sort":[1456185600000]},{"_index":"daily_temperature","_type":"_doc","_id":"VEunPnQBWtRdb_i9xZkw","_score":null,"_source":{"station_id":"c24m124e03","date":"24-02-2016","t_min":4.7,"t_max":17.1,"t_avg":10.9,"week_number":8,"month":2},"sort":[1456272000000]},{"_index":"daily_temperature","_type":"_doc","_id":"bkunPnQBWtRdb_i9xZlS","_score":null,"_source":{"station_id":"c24m124e03","date":"25-02-2016","t_min":7.2,"t_max":13.2,"t_avg":10.2,"week_number":8,"month":2},"sort":[1456358400000]},{"_index":"daily_temperature","_type":"_doc","_id":"iEunPnQBWtRdb_i9xZlr","_score":null,"_source":{"station_id":"c24m124e03","date":"26-02-2016","t_min":4.2,"t_max":12.8,"t_avg":8.5,"week_number":9,"month":2},"sort":[1456444800000]},{"_index":"daily_temperature","_type":"_doc","_id":"bUunPnQBWtRdb_i9xZlQ","_score":null,"_source":{"station_id":"c24m124e03","date":"27-02-2016","t_min":2.7,"t_max":6.8,"t_avg":4.8,"week_number":9,"month":2},"sort":[1456531200000]},{"_index":"daily_temperature","_type":"_doc","_id":"mUunPnQBWtRdb_i9xZmA","_score":null,"_source":{"station_id":"c24m124e03","date":"28-02-2016","t_min":1.9,"t_max":10.8,"t_avg":6.3,"week_number":9,"month":2},"sort":[1456617600000]},{"_index":"daily_temperature","_type":"_doc","_id":"fUunPnQBWtRdb_i9xZlk","_score":null,"_source":{"station_id":"c24m124e03","date":"29-02-2016","t_min":3.7,"t_max":12.6,"t_avg":8.2,"week_number":9,"month":2},"sort":[1456704000000]},{"_index":"daily_temperature","_type":"_doc","_id":"CEunPnQBWtRdb_i9y5tn","_score":null,"_source":{"station_id":"c24m124e03","date":"01-03-2016","t_min":1.4,"t_max":15.5,"t_avg":8.4,"week_number":9,"month":3},"sort":[1456790400000]},{"_index":"daily_temperature","_type":"_doc","_id":"CUunPnQBWtRdb_i9y5tn","_score":null,"_source":{"station_id":"c24m124e03","date":"02-03-2016","t_min":7.7,"t_max":19.1,"t_avg":13.4,"week_number":9,"month":3},"sort":[1456876800000]},{"_index":"daily_temperature","_type":"_doc","_id":"CkunPnQBWtRdb_i9y5tq","_score":null,"_source":{"station_id":"c24m124e03","date":"03-03-2016","t_min":5.6,"t_max":15.3,"t_avg":10.4,"week_number":9,"month":3},"sort":[1456963200000]},{"_index":"daily_temperature","_type":"_doc","_id":"C0unPnQBWtRdb_i9y5tt","_score":null,"_source":{"station_id":"c24m124e03","date":"04-03-2016","t_min":3.8,"t_max":18.9,"t_avg":11.3,"week_number":10,"month":3},"sort":[1457049600000]},{"_index":"daily_temperature","_type":"_doc","_id":"DEunPnQBWtRdb_i9y5tt","_score":null,"_source":{"station_id":"c24m124e03","date":"05-03-2016","t_min":4.4,"t_max":11.3,"t_avg":7.8,"week_number":10,"month":3},"sort":[1457136000000]},{"_index":"daily_temperature","_type":"_doc","_id":"DUunPnQBWtRdb_i9y5tt","_score":null,"_source":{"station_id":"c24m124e03","date":"06-03-2016","t_min":3,"t_max":11.2,"t_avg":7.1,"week_number":10,"month":3},"sort":[1457222400000]},{"_index":"daily_temperature","_type":"_doc","_id":"DkunPnQBWtRdb_i9y5tw","_score":null,"_source":{"station_id":"c24m124e03","date":"07-03-2016","t_min":2.8,"t_max":6.9,"t_avg":4.8,"week_number":10,"month":3},"sort":[1457308800000]},{"_index":"daily_temperature","_type":"_doc","_id":"D0unPnQBWtRdb_i9y5tw","_score":null,"_source":{"station_id":"c24m124e03","date":"08-03-2016","t_min":1.2,"t_max":11,"t_avg":6.1,"week_number":10,"month":3},"sort":[1457395200000]},{"_index":"daily_temperature","_type":"_doc","_id":"EEunPnQBWtRdb_i9y5tz","_score":null,"_source":{"station_id":"c24m124e03","date":"09-03-2016","t_min":1.4,"t_max":11.3,"t_avg":6.3,"week_number":10,"month":3},"sort":[1457481600000]},{"_index":"daily_temperature","_type":"_doc","_id":"EUunPnQBWtRdb_i9y5t0","_score":null,"_source":{"station_id":"c24m124e03","date":"10-03-2016","t_min":2.9,"t_max":10.9,"t_avg":6.9,"week_number":10,"month":3},"sort":[1457568000000]},{"_index":"daily_temperature","_type":"_doc","_id":"EkunPnQBWtRdb_i9y5t1","_score":null,"_source":{"station_id":"c24m124e03","date":"11-03-2016","t_min":0.5,"t_max":13.5,"t_avg":7,"week_number":11,"month":3},"sort":[1457654400000]},{"_index":"daily_temperature","_type":"_doc","_id":"E0unPnQBWtRdb_i9y5t4","_score":null,"_source":{"station_id":"c24m124e03","date":"12-03-2016","t_min":0.7,"t_max":13.3,"t_avg":7,"week_number":11,"month":3},"sort":[1457740800000]},{"_index":"daily_temperature","_type":"_doc","_id":"FEunPnQBWtRdb_i9y5t4","_score":null,"_source":{"station_id":"c24m124e03","date":"13-03-2016","t_min":0.9,"t_max":14.8,"t_avg":7.8,"week_number":11,"month":3},"sort":[1457827200000]},{"_index":"daily_temperature","_type":"_doc","_id":"FUunPnQBWtRdb_i9y5t6","_score":null,"_source":{"station_id":"c24m124e03","date":"14-03-2016","t_min":2.8,"t_max":12.4,"t_avg":7.6,"week_number":11,"month":3},"sort":[1457913600000]},{"_index":"daily_temperature","_type":"_doc","_id":"FkunPnQBWtRdb_i9y5t7","_score":null,"_source":{"station_id":"c24m124e03","date":"15-03-2016","t_min":5,"t_max":12.5,"t_avg":8.8,"week_number":11,"month":3},"sort":[1458000000000]},{"_index":"daily_temperature","_type":"_doc","_id":"F0unPnQBWtRdb_i9y5t_","_score":null,"_source":{"station_id":"c24m124e03","date":"16-03-2016","t_min":2.4,"t_max":15.4,"t_avg":8.9,"week_number":11,"month":3},"sort":[1458086400000]},{"_index":"daily_temperature","_type":"_doc","_id":"GEunPnQBWtRdb_i9y5uA","_score":null,"_source":{"station_id":"c24m124e03","date":"17-03-2016","t_min":2.9,"t_max":13.9,"t_avg":8.4,"week_number":11,"month":3},"sort":[1458172800000]},{"_index":"daily_temperature","_type":"_doc","_id":"GUunPnQBWtRdb_i9y5uB","_score":null,"_source":{"station_id":"c24m124e03","date":"18-03-2016","t_min":6.4,"t_max":14.4,"t_avg":10.4,"week_number":12,"month":3},"sort":[1458259200000]},{"_index":"daily_temperature","_type":"_doc","_id":"GkunPnQBWtRdb_i9y5uB","_score":null,"_source":{"station_id":"c24m124e03","date":"19-03-2016","t_min":8.3,"t_max":14.3,"t_avg":11.3,"week_number":12,"month":3},"sort":[1458345600000]},{"_index":"daily_temperature","_type":"_doc","_id":"G0unPnQBWtRdb_i9y5uC","_score":null,"_source":{"station_id":"c24m124e03","date":"20-03-2016","t_min":4.1,"t_max":15.8,"t_avg":9.9,"week_number":12,"month":3},"sort":[1458432000000]},{"_index":"daily_temperature","_type":"_doc","_id":"HEunPnQBWtRdb_i9y5uC","_score":null,"_source":{"station_id":"c24m124e03","date":"21-03-2016","t_min":7,"t_max":9.7,"t_avg":8.3,"week_number":12,"month":3},"sort":[1458518400000]},{"_index":"daily_temperature","_type":"_doc","_id":"HUunPnQBWtRdb_i9y5uI","_score":null,"_source":{"station_id":"c24m124e03","date":"22-03-2016","t_min":6.5,"t_max":10.9,"t_avg":8.7,"week_number":12,"month":3},"sort":[1458604800000]},{"_index":"daily_temperature","_type":"_doc","_id":"HkunPnQBWtRdb_i9y5uJ","_score":null,"_source":{"station_id":"c24m124e03","date":"23-03-2016","t_min":6.4,"t_max":14.9,"t_avg":10.7,"week_number":12,"month":3},"sort":[1458691200000]},{"_index":"daily_temperature","_type":"_doc","_id":"H0unPnQBWtRdb_i9y5uK","_score":null,"_source":{"station_id":"c24m124e03","date":"24-03-2016","t_min":1.6,"t_max":18.2,"t_avg":9.9,"week_number":12,"month":3},"sort":[1458777600000]},{"_index":"daily_temperature","_type":"_doc","_id":"IEunPnQBWtRdb_i9y5uL","_score":null,"_source":{"station_id":"c24m124e03","date":"25-03-2016","t_min":8.1,"t_max":20.1,"t_avg":14.1,"week_number":13,"month":3},"sort":[1458864000000]},{"_index":"daily_temperature","_type":"_doc","_id":"IUunPnQBWtRdb_i9y5uL","_score":null,"_source":{"station_id":"c24m124e03","date":"26-03-2016","t_min":9,"t_max":21.1,"t_avg":15.1,"week_number":13,"month":3},"sort":[1458950400000]},{"_index":"daily_temperature","_type":"_doc","_id":"IkunPnQBWtRdb_i9y5uN","_score":null,"_source":{"station_id":"c24m124e03","date":"27-03-2016","t_min":10.6,"t_max":17.4,"t_avg":14,"week_number":13,"month":3},"sort":[1459036800000]},{"_index":"daily_temperature","_type":"_doc","_id":"I0unPnQBWtRdb_i9y5uN","_score":null,"_source":{"station_id":"c24m124e03","date":"28-03-2016","t_min":8.8,"t_max":18.4,"t_avg":13.6,"week_number":13,"month":3},"sort":[1459123200000]},{"_index":"daily_temperature","_type":"_doc","_id":"JEunPnQBWtRdb_i9y5uP","_score":null,"_source":{"station_id":"c24m124e03","date":"29-03-2016","t_min":9.7,"t_max":21.7,"t_avg":15.7,"week_number":13,"month":3},"sort":[1459209600000]},{"_index":"daily_temperature","_type":"_doc","_id":"JUunPnQBWtRdb_i9y5uQ","_score":null,"_source":{"station_id":"c24m124e03","date":"30-03-2016","t_min":7.4,"t_max":23.9,"t_avg":15.7,"week_number":13,"month":3},"sort":[1459296000000]},{"_index":"daily_temperature","_type":"_doc","_id":"JkunPnQBWtRdb_i9y5uR","_score":null,"_source":{"station_id":"c24m124e03","date":"31-03-2016","t_min":7.9,"t_max":14.1,"t_avg":11,"week_number":13,"month":3},"sort":[1459382400000]},{"_index":"daily_temperature","_type":"_doc","_id":"J0unPnQBWtRdb_i9y5uV","_score":null,"_source":{"station_id":"c24m124e03","date":"01-04-2016","t_min":3.2,"t_max":13.3,"t_avg":8.2,"week_number":14,"month":4},"sort":[1459468800000]},{"_index":"daily_temperature","_type":"_doc","_id":"KEunPnQBWtRdb_i9y5uV","_score":null,"_source":{"station_id":"c24m124e03","date":"02-04-2016","t_min":1.6,"t_max":16.8,"t_avg":9.2,"week_number":14,"month":4},"sort":[1459555200000]},{"_index":"daily_temperature","_type":"_doc","_id":"KUunPnQBWtRdb_i9y5uV","_score":null,"_source":{"station_id":"c24m124e03","date":"03-04-2016","t_min":5.2,"t_max":18.7,"t_avg":11.9,"week_number":14,"month":4},"sort":[1459641600000]},{"_index":"daily_temperature","_type":"_doc","_id":"KkunPnQBWtRdb_i9y5uZ","_score":null,"_source":{"station_id":"c24m124e03","date":"04-04-2016","t_min":9.5,"t_max":16.9,"t_avg":13.2,"week_number":14,"month":4},"sort":[1459728000000]},{"_index":"daily_temperature","_type":"_doc","_id":"K0unPnQBWtRdb_i9y5uZ","_score":null,"_source":{"station_id":"c24m124e03","date":"05-04-2016","t_min":6.4,"t_max":10.1,"t_avg":8.2,"week_number":14,"month":4},"sort":[1459814400000]},{"_index":"daily_temperature","_type":"_doc","_id":"LEunPnQBWtRdb_i9y5ub","_score":null,"_source":{"station_id":"c24m124e03","date":"06-04-2016","t_min":8.6,"t_max":15.5,"t_avg":12.1,"week_number":14,"month":4},"sort":[1459900800000]},{"_index":"daily_temperature","_type":"_doc","_id":"LUunPnQBWtRdb_i9y5ue","_score":null,"_source":{"station_id":"c24m124e03","date":"07-04-2016","t_min":8.3,"t_max":18.6,"t_avg":13.4,"week_number":14,"month":4},"sort":[1459987200000]},{"_index":"daily_temperature","_type":"_doc","_id":"LkunPnQBWtRdb_i9y5ue","_score":null,"_source":{"station_id":"c24m124e03","date":"08-04-2016","t_min":4.3,"t_max":12.8,"t_avg":8.6,"week_number":15,"month":4},"sort":[1460073600000]},{"_index":"daily_temperature","_type":"_doc","_id":"L0unPnQBWtRdb_i9y5ug","_score":null,"_source":{"station_id":"c24m124e03","date":"09-04-2016","t_min":2.8,"t_max":17.5,"t_avg":10.2,"week_number":15,"month":4},"sort":[1460160000000]},{"_index":"daily_temperature","_type":"_doc","_id":"MEunPnQBWtRdb_i9y5uh","_score":null,"_source":{"station_id":"c24m124e03","date":"10-04-2016","t_min":6.7,"t_max":18.2,"t_avg":12.4,"week_number":15,"month":4},"sort":[1460246400000]},{"_index":"daily_temperature","_type":"_doc","_id":"MUunPnQBWtRdb_i9y5ui","_score":null,"_source":{"station_id":"c24m124e03","date":"11-04-2016","t_min":7.8,"t_max":17.8,"t_avg":12.8,"week_number":15,"month":4},"sort":[1460332800000]},{"_index":"daily_temperature","_type":"_doc","_id":"MkunPnQBWtRdb_i9y5ul","_score":null,"_source":{"station_id":"c24m124e03","date":"12-04-2016","t_min":7.4,"t_max":20.2,"t_avg":13.8,"week_number":15,"month":4},"sort":[1460419200000]},{"_index":"daily_temperature","_type":"_doc","_id":"M0unPnQBWtRdb_i9y5um","_score":null,"_source":{"station_id":"c24m124e03","date":"13-04-2016","t_min":9.2,"t_max":17.3,"t_avg":13.2,"week_number":15,"month":4},"sort":[1460505600000]},{"_index":"daily_temperature","_type":"_doc","_id":"NEunPnQBWtRdb_i9y5un","_score":null,"_source":{"station_id":"c24m124e03","date":"14-04-2016","t_min":7.3,"t_max":21.8,"t_avg":14.6,"week_number":15,"month":4},"sort":[1460592000000]},{"_index":"daily_temperature","_type":"_doc","_id":"NUunPnQBWtRdb_i9y5uo","_score":null,"_source":{"station_id":"c24m124e03","date":"15-04-2016","t_min":8.7,"t_max":23,"t_avg":15.8,"week_number":16,"month":4},"sort":[1460678400000]},{"_index":"daily_temperature","_type":"_doc","_id":"NkunPnQBWtRdb_i9y5ur","_score":null,"_source":{"station_id":"c24m124e03","date":"16-04-2016","t_min":8.6,"t_max":22.5,"t_avg":15.6,"week_number":16,"month":4},"sort":[1460764800000]},{"_index":"daily_temperature","_type":"_doc","_id":"N0unPnQBWtRdb_i9y5us","_score":null,"_source":{"station_id":"c24m124e03","date":"17-04-2016","t_min":11.9,"t_max":19.8,"t_avg":15.8,"week_number":16,"month":4},"sort":[1460851200000]},{"_index":"daily_temperature","_type":"_doc","_id":"OEunPnQBWtRdb_i9y5uu","_score":null,"_source":{"station_id":"c24m124e03","date":"18-04-2016","t_min":10.1,"t_max":16.3,"t_avg":13.2,"week_number":16,"month":4},"sort":[1460937600000]},{"_index":"daily_temperature","_type":"_doc","_id":"OUunPnQBWtRdb_i9y5uu","_score":null,"_source":{"station_id":"c24m124e03","date":"19-04-2016","t_min":8.3,"t_max":11.7,"t_avg":10,"week_number":16,"month":4},"sort":[1461024000000]},{"_index":"daily_temperature","_type":"_doc","_id":"OkunPnQBWtRdb_i9y5ux","_score":null,"_source":{"station_id":"c24m124e03","date":"20-04-2016","t_min":7.9,"t_max":13.4,"t_avg":10.7,"week_number":16,"month":4},"sort":[1461110400000]},{"_index":"daily_temperature","_type":"_doc","_id":"O0unPnQBWtRdb_i9y5ux","_score":null,"_source":{"station_id":"c24m124e03","date":"21-04-2016","t_min":7.9,"t_max":18.4,"t_avg":13.2,"week_number":16,"month":4},"sort":[1461196800000]},{"_index":"daily_temperature","_type":"_doc","_id":"PEunPnQBWtRdb_i9y5uz","_score":null,"_source":{"station_id":"c24m124e03","date":"22-04-2016","t_min":10.8,"t_max":16.4,"t_avg":13.6,"week_number":17,"month":4},"sort":[1461283200000]},{"_index":"daily_temperature","_type":"_doc","_id":"PUunPnQBWtRdb_i9y5u0","_score":null,"_source":{"station_id":"c24m124e03","date":"23-04-2016","t_min":8.1,"t_max":20.8,"t_avg":14.4,"week_number":17,"month":4},"sort":[1461369600000]},{"_index":"daily_temperature","_type":"_doc","_id":"PkunPnQBWtRdb_i9y5u2","_score":null,"_source":{"station_id":"c24m124e03","date":"24-04-2016","t_min":7.4,"t_max":20.8,"t_avg":14.1,"week_number":17,"month":4},"sort":[1461456000000]},{"_index":"daily_temperature","_type":"_doc","_id":"P0unPnQBWtRdb_i9y5u5","_score":null,"_source":{"station_id":"c24m124e03","date":"25-04-2016","t_min":5.7,"t_max":19.6,"t_avg":12.7,"week_number":17,"month":4},"sort":[1461542400000]},{"_index":"daily_temperature","_type":"_doc","_id":"QEunPnQBWtRdb_i9y5u5","_score":null,"_source":{"station_id":"c24m124e03","date":"26-04-2016","t_min":6.7,"t_max":22.8,"t_avg":14.8,"week_number":17,"month":4},"sort":[1461628800000]},{"_index":"daily_temperature","_type":"_doc","_id":"QUunPnQBWtRdb_i9y5u8","_score":null,"_source":{"station_id":"c24m124e03","date":"27-04-2016","t_min":9.9,"t_max":19.1,"t_avg":14.5,"week_number":17,"month":4},"sort":[1461715200000]},{"_index":"daily_temperature","_type":"_doc","_id":"QkunPnQBWtRdb_i9y5u8","_score":null,"_source":{"station_id":"c24m124e03","date":"28-04-2016","t_min":9.2,"t_max":16.5,"t_avg":12.8,"week_number":17,"month":4},"sort":[1461801600000]},{"_index":"daily_temperature","_type":"_doc","_id":"Q0unPnQBWtRdb_i9y5u_","_score":null,"_source":{"station_id":"c24m124e03","date":"29-04-2016","t_min":8.4,"t_max":10.4,"t_avg":9.4,"week_number":18,"month":4},"sort":[1461888000000]},{"_index":"daily_temperature","_type":"_doc","_id":"REunPnQBWtRdb_i9y5u_","_score":null,"_source":{"station_id":"c24m124e03","date":"30-04-2016","t_min":9.7,"t_max":19.1,"t_avg":14.4,"week_number":18,"month":4},"sort":[1461974400000]},{"_index":"daily_temperature","_type":"_doc","_id":"_0unPnQBWtRdb_i90J7k","_score":null,"_source":{"station_id":"c24m124e03","date":"01-05-2016","t_min":5.8,"t_max":17.3,"t_avg":11.6,"week_number":18,"month":5},"sort":[1462060800000]},{"_index":"daily_temperature","_type":"_doc","_id":"_kunPnQBWtRdb_i90J7h","_score":null,"_source":{"station_id":"c24m124e03","date":"02-05-2016","t_min":2.7,"t_max":21.8,"t_avg":12.2,"week_number":18,"month":5},"sort":[1462147200000]},{"_index":"daily_temperature","_type":"_doc","_id":"ZkunPnQBWtRdb_i9z56i","_score":null,"_source":{"station_id":"c24m124e03","date":"03-05-2016","t_min":7.4,"t_max":23.4,"t_avg":15.4,"week_number":18,"month":5},"sort":[1462233600000]},{"_index":"daily_temperature","_type":"_doc","_id":"Z0unPnQBWtRdb_i9z56i","_score":null,"_source":{"station_id":"c24m124e03","date":"04-05-2016","t_min":8.6,"t_max":23.6,"t_avg":16.1,"week_number":18,"month":5},"sort":[1462320000000]},{"_index":"daily_temperature","_type":"_doc","_id":"40unPnQBWtRdb_i90p9d","_score":null,"_source":{"station_id":"c24m124e03","date":"05-05-2016","t_min":7.2,"t_max":15.9,"t_avg":11.6,"week_number":18,"month":5},"sort":[1462406400000]},{"_index":"daily_temperature","_type":"_doc","_id":"5EunPnQBWtRdb_i90p9e","_score":null,"_source":{"station_id":"c24m124e03","date":"06-05-2016","t_min":6.7,"t_max":18.7,"t_avg":12.7,"week_number":19,"month":5},"sort":[1462492800000]},{"_index":"daily_temperature","_type":"_doc","_id":"5UunPnQBWtRdb_i90p9g","_score":null,"_source":{"station_id":"c24m124e03","date":"07-05-2016","t_min":9.9,"t_max":16.9,"t_avg":13.4,"week_number":19,"month":5},"sort":[1462579200000]},{"_index":"daily_temperature","_type":"_doc","_id":"5kunPnQBWtRdb_i90p9i","_score":null,"_source":{"station_id":"c24m124e03","date":"08-05-2016","t_min":10.7,"t_max":17.6,"t_avg":14.2,"week_number":19,"month":5},"sort":[1462665600000]},{"_index":"daily_temperature","_type":"_doc","_id":"50unPnQBWtRdb_i90p9i","_score":null,"_source":{"station_id":"c24m124e03","date":"09-05-2016","t_min":9.6,"t_max":16.9,"t_avg":13.2,"week_number":19,"month":5},"sort":[1462752000000]},{"_index":"daily_temperature","_type":"_doc","_id":"6EunPnQBWtRdb_i90p9j","_score":null,"_source":{"station_id":"c24m124e03","date":"10-05-2016","t_min":7.9,"t_max":14.5,"t_avg":11.2,"week_number":19,"month":5},"sort":[1462838400000]},{"_index":"daily_temperature","_type":"_doc","_id":"6UunPnQBWtRdb_i90p9k","_score":null,"_source":{"station_id":"c24m124e03","date":"11-05-2016","t_min":8.8,"t_max":18.3,"t_avg":13.6,"week_number":19,"month":5},"sort":[1462924800000]},{"_index":"daily_temperature","_type":"_doc","_id":"6kunPnQBWtRdb_i90p9k","_score":null,"_source":{"station_id":"c24m124e03","date":"12-05-2016","t_min":9.4,"t_max":17.1,"t_avg":13.2,"week_number":19,"month":5},"sort":[1463011200000]},{"_index":"daily_temperature","_type":"_doc","_id":"60unPnQBWtRdb_i90p9s","_score":null,"_source":{"station_id":"c24m124e03","date":"13-05-2016","t_min":8.9,"t_max":17.2,"t_avg":13.1,"week_number":20,"month":5},"sort":[1463097600000]},{"_index":"daily_temperature","_type":"_doc","_id":"7EunPnQBWtRdb_i90p9u","_score":null,"_source":{"station_id":"c24m124e03","date":"14-05-2016","t_min":9.2,"t_max":20.3,"t_avg":14.8,"week_number":20,"month":5},"sort":[1463184000000]},{"_index":"daily_temperature","_type":"_doc","_id":"7UunPnQBWtRdb_i90p9v","_score":null,"_source":{"station_id":"c24m124e03","date":"15-05-2016","t_min":11.2,"t_max":21.1,"t_avg":16.1,"week_number":20,"month":5},"sort":[1463270400000]},{"_index":"daily_temperature","_type":"_doc","_id":"7kunPnQBWtRdb_i90p9y","_score":null,"_source":{"station_id":"c24m124e03","date":"16-05-2016","t_min":10.6,"t_max":22.7,"t_avg":16.6,"week_number":20,"month":5},"sort":[1463356800000]},{"_index":"daily_temperature","_type":"_doc","_id":"70unPnQBWtRdb_i90p9z","_score":null,"_source":{"station_id":"c24m124e03","date":"17-05-2016","t_min":8.7,"t_max":20.4,"t_avg":14.6,"week_number":20,"month":5},"sort":[1463443200000]},{"_index":"daily_temperature","_type":"_doc","_id":"8EunPnQBWtRdb_i90p90","_score":null,"_source":{"station_id":"c24m124e03","date":"18-05-2016","t_min":10.4,"t_max":24.6,"t_avg":17.5,"week_number":20,"month":5},"sort":[1463529600000]},{"_index":"daily_temperature","_type":"_doc","_id":"8UunPnQBWtRdb_i90p93","_score":null,"_source":{"station_id":"c24m124e03","date":"19-05-2016","t_min":12.1,"t_max":26.2,"t_avg":19.1,"week_number":20,"month":5},"sort":[1463616000000]},{"_index":"daily_temperature","_type":"_doc","_id":"8kunPnQBWtRdb_i90p94","_score":null,"_source":{"station_id":"c24m124e03","date":"20-05-2016","t_min":11.9,"t_max":25.4,"t_avg":18.6,"week_number":21,"month":5},"sort":[1463702400000]},{"_index":"daily_temperature","_type":"_doc","_id":"80unPnQBWtRdb_i90p94","_score":null,"_source":{"station_id":"c24m124e03","date":"21-05-2016","t_min":10.3,"t_max":26,"t_avg":18.1,"week_number":21,"month":5},"sort":[1463788800000]},{"_index":"daily_temperature","_type":"_doc","_id":"9EunPnQBWtRdb_i90p97","_score":null,"_source":{"station_id":"c24m124e03","date":"22-05-2016","t_min":10.7,"t_max":25.1,"t_avg":17.9,"week_number":21,"month":5},"sort":[1463875200000]},{"_index":"daily_temperature","_type":"_doc","_id":"EEunPnQBWtRdb_i91aAU","_score":null,"_source":{"station_id":"c24m124e03","date":"23-05-2016","t_min":9,"t_max":21.2,"t_avg":15.1,"week_number":21,"month":5},"sort":[1463961600000]},{"_index":"daily_temperature","_type":"_doc","_id":"D0unPnQBWtRdb_i91aAU","_score":null,"_source":{"station_id":"c24m124e03","date":"24-05-2016","t_min":9.4,"t_max":26.8,"t_avg":18.1,"week_number":21,"month":5},"sort":[1464048000000]},{"_index":"daily_temperature","_type":"_doc","_id":"DkunPnQBWtRdb_i91aAU","_score":null,"_source":{"station_id":"c24m124e03","date":"25-05-2016","t_min":11.8,"t_max":28.5,"t_avg":20.1,"week_number":21,"month":5},"sort":[1464134400000]},{"_index":"daily_temperature","_type":"_doc","_id":"DUunPnQBWtRdb_i91aAT","_score":null,"_source":{"station_id":"c24m124e03","date":"26-05-2016","t_min":13.2,"t_max":24.4,"t_avg":18.8,"week_number":21,"month":5},"sort":[1464220800000]},{"_index":"daily_temperature","_type":"_doc","_id":"DEunPnQBWtRdb_i91aAR","_score":null,"_source":{"station_id":"c24m124e03","date":"27-05-2016","t_min":11.6,"t_max":29.7,"t_avg":20.6,"week_number":22,"month":5},"sort":[1464307200000]},{"_index":"daily_temperature","_type":"_doc","_id":"C0unPnQBWtRdb_i91aAR","_score":null,"_source":{"station_id":"c24m124e03","date":"28-05-2016","t_min":14.2,"t_max":26.6,"t_avg":20.4,"week_number":22,"month":5},"sort":[1464393600000]},{"_index":"daily_temperature","_type":"_doc","_id":"CkunPnQBWtRdb_i91aAR","_score":null,"_source":{"station_id":"c24m124e03","date":"29-05-2016","t_min":12.4,"t_max":21.5,"t_avg":16.9,"week_number":22,"month":5},"sort":[1464480000000]},{"_index":"daily_temperature","_type":"_doc","_id":"CUunPnQBWtRdb_i91aAP","_score":null,"_source":{"station_id":"c24m124e03","date":"30-05-2016","t_min":13,"t_max":22.9,"t_avg":17.9,"week_number":22,"month":5},"sort":[1464566400000]},{"_index":"daily_temperature","_type":"_doc","_id":"CEunPnQBWtRdb_i91aAP","_score":null,"_source":{"station_id":"c24m124e03","date":"31-05-2016","t_min":12.2,"t_max":24.1,"t_avg":18.1,"week_number":22,"month":5},"sort":[1464652800000]},{"_index":"daily_temperature","_type":"_doc","_id":"LEunPnQBWtRdb_i9zJyQ","_score":null,"_source":{"station_id":"c24m124e03","date":"01-06-2016","t_min":11.3,"t_max":26.8,"t_avg":19.1,"week_number":22,"month":6},"sort":[1464739200000]},{"_index":"daily_temperature","_type":"_doc","_id":"PkunPnQBWtRdb_i9zJyX","_score":null,"_source":{"station_id":"c24m124e03","date":"02-06-2016","t_min":9.5,"t_max":28.1,"t_avg":18.8,"week_number":22,"month":6},"sort":[1464825600000]},{"_index":"daily_temperature","_type":"_doc","_id":"M0unPnQBWtRdb_i9zJyT","_score":null,"_source":{"station_id":"c24m124e03","date":"03-06-2016","t_min":13.4,"t_max":27.4,"t_avg":20.4,"week_number":23,"month":6},"sort":[1464912000000]},{"_index":"daily_temperature","_type":"_doc","_id":"XEunPnQBWtRdb_i9zJyf","_score":null,"_source":{"station_id":"c24m124e03","date":"04-06-2016","t_min":13.4,"t_max":25.7,"t_avg":19.6,"week_number":23,"month":6},"sort":[1464998400000]},{"_index":"daily_temperature","_type":"_doc","_id":"XkunPnQBWtRdb_i9zJyf","_score":null,"_source":{"station_id":"c24m124e03","date":"05-06-2016","t_min":12.9,"t_max":26.3,"t_avg":19.6,"week_number":23,"month":6},"sort":[1465084800000]},{"_index":"daily_temperature","_type":"_doc","_id":"L0unPnQBWtRdb_i9zJyS","_score":null,"_source":{"station_id":"c24m124e03","date":"06-06-2016","t_min":13.4,"t_max":28.3,"t_avg":20.9,"week_number":23,"month":6},"sort":[1465171200000]},{"_index":"daily_temperature","_type":"_doc","_id":"R0unPnQBWtRdb_i9zJyZ","_score":null,"_source":{"station_id":"c24m124e03","date":"07-06-2016","t_min":14.1,"t_max":27.9,"t_avg":21,"week_number":23,"month":6},"sort":[1465257600000]},{"_index":"daily_temperature","_type":"_doc","_id":"YUunPnQBWtRdb_i9zJyh","_score":null,"_source":{"station_id":"c24m124e03","date":"08-06-2016","t_min":13,"t_max":31.3,"t_avg":22.1,"week_number":23,"month":6},"sort":[1465344000000]},{"_index":"daily_temperature","_type":"_doc","_id":"zkunPnQBWtRdb_i90J54","_score":null,"_source":{"station_id":"c24m124e03","date":"09-06-2016","t_min":16.9,"t_max":33.1,"t_avg":25,"week_number":23,"month":6},"sort":[1465430400000]},{"_index":"daily_temperature","_type":"_doc","_id":"zEunPnQBWtRdb_i90J5w","_score":null,"_source":{"station_id":"c24m124e03","date":"10-06-2016","t_min":16.2,"t_max":33.6,"t_avg":24.9,"week_number":24,"month":6},"sort":[1465516800000]},{"_index":"daily_temperature","_type":"_doc","_id":"y0unPnQBWtRdb_i90J5u","_score":null,"_source":{"station_id":"c24m124e03","date":"11-06-2016","t_min":16.4,"t_max":25.8,"t_avg":21.1,"week_number":24,"month":6},"sort":[1465603200000]},{"_index":"daily_temperature","_type":"_doc","_id":"ykunPnQBWtRdb_i90J5u","_score":null,"_source":{"station_id":"c24m124e03","date":"12-06-2016","t_min":15.7,"t_max":31.2,"t_avg":23.4,"week_number":24,"month":6},"sort":[1465689600000]},{"_index":"daily_temperature","_type":"_doc","_id":"yUunPnQBWtRdb_i90J5t","_score":null,"_source":{"station_id":"c24m124e03","date":"13-06-2016","t_min":17.9,"t_max":32.6,"t_avg":25.2,"week_number":24,"month":6},"sort":[1465776000000]},{"_index":"daily_temperature","_type":"_doc","_id":"yEunPnQBWtRdb_i90J5r","_score":null,"_source":{"station_id":"c24m124e03","date":"14-06-2016","t_min":20.2,"t_max":30.6,"t_avg":25.4,"week_number":24,"month":6},"sort":[1465862400000]},{"_index":"daily_temperature","_type":"_doc","_id":"x0unPnQBWtRdb_i90J5q","_score":null,"_source":{"station_id":"c24m124e03","date":"15-06-2016","t_min":18.8,"t_max":28.6,"t_avg":23.7,"week_number":24,"month":6},"sort":[1465948800000]},{"_index":"daily_temperature","_type":"_doc","_id":"xkunPnQBWtRdb_i90J5q","_score":null,"_source":{"station_id":"c24m124e03","date":"16-06-2016","t_min":13.6,"t_max":21.4,"t_avg":17.5,"week_number":24,"month":6},"sort":[1466035200000]},{"_index":"daily_temperature","_type":"_doc","_id":"xUunPnQBWtRdb_i90J5p","_score":null,"_source":{"station_id":"c24m124e03","date":"17-06-2016","t_min":12.2,"t_max":24.4,"t_avg":18.3,"week_number":25,"month":6},"sort":[1466121600000]},{"_index":"daily_temperature","_type":"_doc","_id":"xEunPnQBWtRdb_i90J5o","_score":null,"_source":{"station_id":"c24m124e03","date":"18-06-2016","t_min":12.4,"t_max":23.6,"t_avg":18,"week_number":25,"month":6},"sort":[1466208000000]},{"_index":"daily_temperature","_type":"_doc","_id":"w0unPnQBWtRdb_i90J5n","_score":null,"_source":{"station_id":"c24m124e03","date":"19-06-2016","t_min":10.8,"t_max":25.9,"t_avg":18.4,"week_number":25,"month":6},"sort":[1466294400000]},{"_index":"daily_temperature","_type":"_doc","_id":"wkunPnQBWtRdb_i90J5m","_score":null,"_source":{"station_id":"c24m124e03","date":"20-06-2016","t_min":11.4,"t_max":25.9,"t_avg":18.6,"week_number":25,"month":6},"sort":[1466380800000]},{"_index":"daily_temperature","_type":"_doc","_id":"wUunPnQBWtRdb_i90J5m","_score":null,"_source":{"station_id":"c24m124e03","date":"21-06-2016","t_min":12.1,"t_max":27.9,"t_avg":20,"week_number":25,"month":6},"sort":[1466467200000]},{"_index":"daily_temperature","_type":"_doc","_id":"wEunPnQBWtRdb_i90J5l","_score":null,"_source":{"station_id":"c24m124e03","date":"22-06-2016","t_min":12.9,"t_max":28,"t_avg":20.4,"week_number":25,"month":6},"sort":[1466553600000]},{"_index":"daily_temperature","_type":"_doc","_id":"v0unPnQBWtRdb_i90J5k","_score":null,"_source":{"station_id":"c24m124e03","date":"23-06-2016","t_min":13.4,"t_max":31.3,"t_avg":22.4,"week_number":25,"month":6},"sort":[1466640000000]},{"_index":"daily_temperature","_type":"_doc","_id":"vkunPnQBWtRdb_i90J5j","_score":null,"_source":{"station_id":"c24m124e03","date":"24-06-2016","t_min":15.6,"t_max":33.8,"t_avg":24.7,"week_number":26,"month":6},"sort":[1466726400000]},{"_index":"daily_temperature","_type":"_doc","_id":"vUunPnQBWtRdb_i90J5f","_score":null,"_source":{"station_id":"c24m124e03","date":"25-06-2016","t_min":15.6,"t_max":27.1,"t_avg":21.4,"week_number":26,"month":6},"sort":[1466812800000]},{"_index":"daily_temperature","_type":"_doc","_id":"vEunPnQBWtRdb_i90J5a","_score":null,"_source":{"station_id":"c24m124e03","date":"26-06-2016","t_min":16.7,"t_max":24.2,"t_avg":20.4,"week_number":26,"month":6},"sort":[1466899200000]},{"_index":"daily_temperature","_type":"_doc","_id":"u0unPnQBWtRdb_i90J5Y","_score":null,"_source":{"station_id":"c24m124e03","date":"27-06-2016","t_min":14.9,"t_max":27.3,"t_avg":21.1,"week_number":26,"month":6},"sort":[1466985600000]},{"_index":"daily_temperature","_type":"_doc","_id":"ukunPnQBWtRdb_i90J5W","_score":null,"_source":{"station_id":"c24m124e03","date":"28-06-2016","t_min":14.9,"t_max":30,"t_avg":22.4,"week_number":26,"month":6},"sort":[1467072000000]},{"_index":"daily_temperature","_type":"_doc","_id":"uUunPnQBWtRdb_i90J5V","_score":null,"_source":{"station_id":"c24m124e03","date":"29-06-2016","t_min":17.3,"t_max":30.4,"t_avg":23.9,"week_number":26,"month":6},"sort":[1467158400000]},{"_index":"daily_temperature","_type":"_doc","_id":"uEunPnQBWtRdb_i90J5S","_score":null,"_source":{"station_id":"c24m124e03","date":"30-06-2016","t_min":17.3,"t_max":32.9,"t_avg":25.1,"week_number":26,"month":6},"sort":[1467244800000]},{"_index":"daily_temperature","_type":"_doc","_id":"skunPnQBWtRdb_i9y5oG","_score":null,"_source":{"station_id":"c24m124e03","date":"01-07-2016","t_min":17.4,"t_max":31.8,"t_avg":24.6,"week_number":27,"month":7},"sort":[1467331200000]},{"_index":"daily_temperature","_type":"_doc","_id":"zEunPnQBWtRdb_i9y5oO","_score":null,"_source":{"station_id":"c24m124e03","date":"02-07-2016","t_min":16.6,"t_max":33.2,"t_avg":24.9,"week_number":27,"month":7},"sort":[1467417600000]},{"_index":"daily_temperature","_type":"_doc","_id":"wUunPnQBWtRdb_i9y5oK","_score":null,"_source":{"station_id":"c24m124e03","date":"03-07-2016","t_min":18.6,"t_max":27.5,"t_avg":23.1,"week_number":27,"month":7},"sort":[1467504000000]},{"_index":"daily_temperature","_type":"_doc","_id":"Z0unPnQBWtRdb_i9yprM","_score":null,"_source":{"station_id":"c24m124e03","date":"04-07-2016","t_min":16.6,"t_max":26.6,"t_avg":21.6,"week_number":27,"month":7},"sort":[1467590400000]},{"_index":"daily_temperature","_type":"_doc","_id":"yEunPnQBWtRdb_i9y5oO","_score":null,"_source":{"station_id":"c24m124e03","date":"05-07-2016","t_min":15.6,"t_max":30.8,"t_avg":23.2,"week_number":27,"month":7},"sort":[1467676800000]},{"_index":"daily_temperature","_type":"_doc","_id":"fkunPnQBWtRdb_i9yprW","_score":null,"_source":{"station_id":"c24m124e03","date":"06-07-2016","t_min":17.2,"t_max":31.2,"t_avg":24.2,"week_number":27,"month":7},"sort":[1467763200000]},{"_index":"daily_temperature","_type":"_doc","_id":"cUunPnQBWtRdb_i9yprR","_score":null,"_source":{"station_id":"c24m124e03","date":"07-07-2016","t_min":16.7,"t_max":27.1,"t_avg":21.9,"week_number":27,"month":7},"sort":[1467849600000]},{"_index":"daily_temperature","_type":"_doc","_id":"wkunPnQBWtRdb_i9y5oL","_score":null,"_source":{"station_id":"c24m124e03","date":"08-07-2016","t_min":16.4,"t_max":33.3,"t_avg":24.9,"week_number":28,"month":7},"sort":[1467936000000]},{"_index":"daily_temperature","_type":"_doc","_id":"XEunPnQBWtRdb_i9yprH","_score":null,"_source":{"station_id":"c24m124e03","date":"09-07-2016","t_min":18.1,"t_max":30.2,"t_avg":24.1,"week_number":28,"month":7},"sort":[1468022400000]},{"_index":"daily_temperature","_type":"_doc","_id":"vkunPnQBWtRdb_i9y5oK","_score":null,"_source":{"station_id":"c24m124e03","date":"10-07-2016","t_min":17.2,"t_max":35.3,"t_avg":26.2,"week_number":28,"month":7},"sort":[1468108800000]},{"_index":"daily_temperature","_type":"_doc","_id":"fUunPnQBWtRdb_i9yprW","_score":null,"_source":{"station_id":"c24m124e03","date":"11-07-2016","t_min":19.1,"t_max":34.4,"t_avg":26.8,"week_number":28,"month":7},"sort":[1468195200000]},{"_index":"daily_temperature","_type":"_doc","_id":"YEunPnQBWtRdb_i9yprI","_score":null,"_source":{"station_id":"c24m124e03","date":"12-07-2016","t_min":18.1,"t_max":32.9,"t_avg":25.5,"week_number":28,"month":7},"sort":[1468281600000]},{"_index":"daily_temperature","_type":"_doc","_id":"y0unPnQBWtRdb_i9y5oO","_score":null,"_source":{"station_id":"c24m124e03","date":"13-07-2016","t_min":17.8,"t_max":21.3,"t_avg":19.6,"week_number":28,"month":7},"sort":[1468368000000]},{"_index":"daily_temperature","_type":"_doc","_id":"XUunPnQBWtRdb_i9yprH","_score":null,"_source":{"station_id":"c24m124e03","date":"14-07-2016","t_min":17.1,"t_max":26.5,"t_avg":21.8,"week_number":28,"month":7},"sort":[1468454400000]},{"_index":"daily_temperature","_type":"_doc","_id":"fEunPnQBWtRdb_i9yprW","_score":null,"_source":{"station_id":"c24m124e03","date":"15-07-2016","t_min":16.5,"t_max":24.9,"t_avg":20.7,"week_number":29,"month":7},"sort":[1468540800000]},{"_index":"daily_temperature","_type":"_doc","_id":"l0unPnQBWtRdb_i9ypr0","_score":null,"_source":{"station_id":"c24m124e03","date":"16-07-2016","t_min":14.4,"t_max":27.3,"t_avg":20.9,"week_number":29,"month":7},"sort":[1468627200000]},{"_index":"daily_temperature","_type":"_doc","_id":"jUunPnQBWtRdb_i9yprc","_score":null,"_source":{"station_id":"c24m124e03","date":"17-07-2016","t_min":13.8,"t_max":29.4,"t_avg":21.6,"week_number":29,"month":7},"sort":[1468713600000]},{"_index":"daily_temperature","_type":"_doc","_id":"e0unPnQBWtRdb_i9yprW","_score":null,"_source":{"station_id":"c24m124e03","date":"18-07-2016","t_min":12.9,"t_max":28.9,"t_avg":20.9,"week_number":29,"month":7},"sort":[1468800000000]},{"_index":"daily_temperature","_type":"_doc","_id":"oEunPnQBWtRdb_i9ypr8","_score":null,"_source":{"station_id":"c24m124e03","date":"19-07-2016","t_min":13.7,"t_max":33.7,"t_avg":23.7,"week_number":29,"month":7},"sort":[1468886400000]},{"_index":"daily_temperature","_type":"_doc","_id":"eEunPnQBWtRdb_i9yprT","_score":null,"_source":{"station_id":"c24m124e03","date":"20-07-2016","t_min":17.2,"t_max":33.3,"t_avg":25.2,"week_number":29,"month":7},"sort":[1468972800000]},{"_index":"daily_temperature","_type":"_doc","_id":"x0unPnQBWtRdb_i9y5oN","_score":null,"_source":{"station_id":"c24m124e03","date":"21-07-2016","t_min":20.4,"t_max":35.6,"t_avg":28,"week_number":29,"month":7},"sort":[1469059200000]},{"_index":"daily_temperature","_type":"_doc","_id":"uEunPnQBWtRdb_i9y5oH","_score":null,"_source":{"station_id":"c24m124e03","date":"22-07-2016","t_min":15.7,"t_max":27.5,"t_avg":21.6,"week_number":30,"month":7},"sort":[1469145600000]},{"_index":"daily_temperature","_type":"_doc","_id":"SkunPnQBWtRdb_i9ypq_","_score":null,"_source":{"station_id":"c24m124e03","date":"23-07-2016","t_min":16.5,"t_max":28.7,"t_avg":22.6,"week_number":30,"month":7},"sort":[1469232000000]},{"_index":"daily_temperature","_type":"_doc","_id":"SEunPnQBWtRdb_i9ypq_","_score":null,"_source":{"station_id":"c24m124e03","date":"24-07-2016","t_min":15.9,"t_max":28.4,"t_avg":22.1,"week_number":30,"month":7},"sort":[1469318400000]},{"_index":"daily_temperature","_type":"_doc","_id":"p0unPnQBWtRdb_i9ypr_","_score":null,"_source":{"station_id":"c24m124e03","date":"25-07-2016","t_min":16.7,"t_max":31,"t_avg":23.9,"week_number":30,"month":7},"sort":[1469404800000]},{"_index":"daily_temperature","_type":"_doc","_id":"VkunPnQBWtRdb_i9yprC","_score":null,"_source":{"station_id":"c24m124e03","date":"26-07-2016","t_min":17.1,"t_max":32.1,"t_avg":24.6,"week_number":30,"month":7},"sort":[1469491200000]},{"_index":"daily_temperature","_type":"_doc","_id":"sUunPnQBWtRdb_i9y5oF","_score":null,"_source":{"station_id":"c24m124e03","date":"27-07-2016","t_min":18.2,"t_max":33.3,"t_avg":25.8,"week_number":30,"month":7},"sort":[1469577600000]},{"_index":"daily_temperature","_type":"_doc","_id":"TEunPnQBWtRdb_i9ypq_","_score":null,"_source":{"station_id":"c24m124e03","date":"28-07-2016","t_min":16.9,"t_max":32.7,"t_avg":24.8,"week_number":30,"month":7},"sort":[1469664000000]},{"_index":"daily_temperature","_type":"_doc","_id":"V0unPnQBWtRdb_i9yprC","_score":null,"_source":{"station_id":"c24m124e03","date":"29-07-2016","t_min":16.2,"t_max":34,"t_avg":25.1,"week_number":31,"month":7},"sort":[1469750400000]},{"_index":"daily_temperature","_type":"_doc","_id":"1UunPnQBWtRdb_i9y5oQ","_score":null,"_source":{"station_id":"c24m124e03","date":"30-07-2016","t_min":20.6,"t_max":36.9,"t_avg":28.8,"week_number":31,"month":7},"sort":[1469836800000]},{"_index":"daily_temperature","_type":"_doc","_id":"dUunPnQBWtRdb_i9yprT","_score":null,"_source":{"station_id":"c24m124e03","date":"31-07-2016","t_min":25.2,"t_max":36.4,"t_avg":30.8,"week_number":31,"month":7},"sort":[1469923200000]},{"_index":"daily_temperature","_type":"_doc","_id":"RUunPnQBWtRdb_i9y5vA","_score":null,"_source":{"station_id":"c24m124e03","date":"01-08-2016","t_min":20.1,"t_max":29.3,"t_avg":24.7,"week_number":31,"month":8},"sort":[1470009600000]},{"_index":"daily_temperature","_type":"_doc","_id":"RkunPnQBWtRdb_i9y5vD","_score":null,"_source":{"station_id":"c24m124e03","date":"02-08-2016","t_min":16.7,"t_max":32.3,"t_avg":24.5,"week_number":31,"month":8},"sort":[1470096000000]},{"_index":"daily_temperature","_type":"_doc","_id":"R0unPnQBWtRdb_i9y5vD","_score":null,"_source":{"station_id":"c24m124e03","date":"03-08-2016","t_min":17.7,"t_max":33.6,"t_avg":25.6,"week_number":31,"month":8},"sort":[1470182400000]},{"_index":"daily_temperature","_type":"_doc","_id":"SEunPnQBWtRdb_i9y5vD","_score":null,"_source":{"station_id":"c24m124e03","date":"04-08-2016","t_min":17.8,"t_max":36.6,"t_avg":27.2,"week_number":31,"month":8},"sort":[1470268800000]},{"_index":"daily_temperature","_type":"_doc","_id":"SUunPnQBWtRdb_i9y5vH","_score":null,"_source":{"station_id":"c24m124e03","date":"05-08-2016","t_min":19.7,"t_max":27.1,"t_avg":23.4,"week_number":32,"month":8},"sort":[1470355200000]},{"_index":"daily_temperature","_type":"_doc","_id":"SkunPnQBWtRdb_i9y5vL","_score":null,"_source":{"station_id":"c24m124e03","date":"06-08-2016","t_min":17.4,"t_max":29.1,"t_avg":23.2,"week_number":32,"month":8},"sort":[1470441600000]},{"_index":"daily_temperature","_type":"_doc","_id":"S0unPnQBWtRdb_i9y5vM","_score":null,"_source":{"station_id":"c24m124e03","date":"07-08-2016","t_min":16.5,"t_max":29.8,"t_avg":23.1,"week_number":32,"month":8},"sort":[1470528000000]},{"_index":"daily_temperature","_type":"_doc","_id":"TEunPnQBWtRdb_i9y5vN","_score":null,"_source":{"station_id":"c24m124e03","date":"08-08-2016","t_min":14.8,"t_max":29.8,"t_avg":22.3,"week_number":32,"month":8},"sort":[1470614400000]},{"_index":"daily_temperature","_type":"_doc","_id":"TUunPnQBWtRdb_i9y5vN","_score":null,"_source":{"station_id":"c24m124e03","date":"09-08-2016","t_min":15.7,"t_max":31.2,"t_avg":23.4,"week_number":32,"month":8},"sort":[1470700800000]},{"_index":"daily_temperature","_type":"_doc","_id":"TkunPnQBWtRdb_i9y5vO","_score":null,"_source":{"station_id":"c24m124e03","date":"10-08-2016","t_min":16,"t_max":21.7,"t_avg":18.9,"week_number":32,"month":8},"sort":[1470787200000]},{"_index":"daily_temperature","_type":"_doc","_id":"T0unPnQBWtRdb_i9y5vO","_score":null,"_source":{"station_id":"c24m124e03","date":"11-08-2016","t_min":15.5,"t_max":26.3,"t_avg":20.9,"week_number":32,"month":8},"sort":[1470873600000]},{"_index":"daily_temperature","_type":"_doc","_id":"UEunPnQBWtRdb_i9y5vP","_score":null,"_source":{"station_id":"c24m124e03","date":"12-08-2016","t_min":15.3,"t_max":25.9,"t_avg":20.6,"week_number":33,"month":8},"sort":[1470960000000]},{"_index":"daily_temperature","_type":"_doc","_id":"UUunPnQBWtRdb_i9y5vS","_score":null,"_source":{"station_id":"c24m124e03","date":"13-08-2016","t_min":13.7,"t_max":27.8,"t_avg":20.8,"week_number":33,"month":8},"sort":[1471046400000]},{"_index":"daily_temperature","_type":"_doc","_id":"UkunPnQBWtRdb_i9y5vT","_score":null,"_source":{"station_id":"c24m124e03","date":"14-08-2016","t_min":15,"t_max":27.6,"t_avg":21.3,"week_number":33,"month":8},"sort":[1471132800000]},{"_index":"daily_temperature","_type":"_doc","_id":"U0unPnQBWtRdb_i9y5vT","_score":null,"_source":{"station_id":"c24m124e03","date":"15-08-2016","t_min":13.6,"t_max":31.5,"t_avg":22.6,"week_number":33,"month":8},"sort":[1471219200000]},{"_index":"daily_temperature","_type":"_doc","_id":"VEunPnQBWtRdb_i9y5vT","_score":null,"_source":{"station_id":"c24m124e03","date":"16-08-2016","t_min":18.4,"t_max":23.3,"t_avg":20.9,"week_number":33,"month":8},"sort":[1471305600000]},{"_index":"daily_temperature","_type":"_doc","_id":"VUunPnQBWtRdb_i9y5vl","_score":null,"_source":{"station_id":"c24m124e03","date":"17-08-2016","t_min":16.1,"t_max":32.8,"t_avg":24.4,"week_number":33,"month":8},"sort":[1471392000000]},{"_index":"daily_temperature","_type":"_doc","_id":"VkunPnQBWtRdb_i9y5vm","_score":null,"_source":{"station_id":"c24m124e03","date":"18-08-2016","t_min":20.2,"t_max":33.5,"t_avg":26.9,"week_number":33,"month":8},"sort":[1471478400000]},{"_index":"daily_temperature","_type":"_doc","_id":"V0unPnQBWtRdb_i9y5vm","_score":null,"_source":{"station_id":"c24m124e03","date":"19-08-2016","t_min":18.2,"t_max":35.4,"t_avg":26.8,"week_number":34,"month":8},"sort":[1471564800000]},{"_index":"daily_temperature","_type":"_doc","_id":"WEunPnQBWtRdb_i9y5vs","_score":null,"_source":{"station_id":"c24m124e03","date":"20-08-2016","t_min":21.3,"t_max":33.9,"t_avg":27.6,"week_number":34,"month":8},"sort":[1471651200000]},{"_index":"daily_temperature","_type":"_doc","_id":"WUunPnQBWtRdb_i9y5vt","_score":null,"_source":{"station_id":"c24m124e03","date":"21-08-2016","t_min":13.5,"t_max":24.9,"t_avg":19.2,"week_number":34,"month":8},"sort":[1471737600000]},{"_index":"daily_temperature","_type":"_doc","_id":"E0unPnQBWtRdb_i9zZ3s","_score":null,"_source":{"station_id":"c24m124e03","date":"22-08-2016","t_min":18.1,"t_max":31.2,"t_avg":24.6,"week_number":34,"month":8},"sort":[1471824000000]},{"_index":"daily_temperature","_type":"_doc","_id":"EkunPnQBWtRdb_i9zZ3s","_score":null,"_source":{"station_id":"c24m124e03","date":"23-08-2016","t_min":16.3,"t_max":29,"t_avg":22.6,"week_number":34,"month":8},"sort":[1471910400000]},{"_index":"daily_temperature","_type":"_doc","_id":"EUunPnQBWtRdb_i9zZ3r","_score":null,"_source":{"station_id":"c24m124e03","date":"24-08-2016","t_min":16.2,"t_max":28.7,"t_avg":22.4,"week_number":34,"month":8},"sort":[1471996800000]},{"_index":"daily_temperature","_type":"_doc","_id":"EEunPnQBWtRdb_i9zZ3r","_score":null,"_source":{"station_id":"c24m124e03","date":"25-08-2016","t_min":14.8,"t_max":27.9,"t_avg":21.4,"week_number":34,"month":8},"sort":[1472083200000]},{"_index":"daily_temperature","_type":"_doc","_id":"D0unPnQBWtRdb_i9zZ3q","_score":null,"_source":{"station_id":"c24m124e03","date":"26-08-2016","t_min":14.3,"t_max":29.1,"t_avg":21.7,"week_number":35,"month":8},"sort":[1472169600000]},{"_index":"daily_temperature","_type":"_doc","_id":"DkunPnQBWtRdb_i9zZ3p","_score":null,"_source":{"station_id":"c24m124e03","date":"27-08-2016","t_min":15.6,"t_max":33.9,"t_avg":24.8,"week_number":35,"month":8},"sort":[1472256000000]},{"_index":"daily_temperature","_type":"_doc","_id":"DUunPnQBWtRdb_i9zZ3o","_score":null,"_source":{"station_id":"c24m124e03","date":"28-08-2016","t_min":18.7,"t_max":34.7,"t_avg":26.7,"week_number":35,"month":8},"sort":[1472342400000]},{"_index":"daily_temperature","_type":"_doc","_id":"DEunPnQBWtRdb_i9zZ3n","_score":null,"_source":{"station_id":"c24m124e03","date":"29-08-2016","t_min":19.6,"t_max":29.1,"t_avg":24.4,"week_number":35,"month":8},"sort":[1472428800000]},{"_index":"daily_temperature","_type":"_doc","_id":"C0unPnQBWtRdb_i9zZ3n","_score":null,"_source":{"station_id":"c24m124e03","date":"30-08-2016","t_min":19.3,"t_max":29.4,"t_avg":24.4,"week_number":35,"month":8},"sort":[1472515200000]},{"_index":"daily_temperature","_type":"_doc","_id":"CkunPnQBWtRdb_i9zZ3m","_score":null,"_source":{"station_id":"c24m124e03","date":"31-08-2016","t_min":17.4,"t_max":27.9,"t_avg":22.6,"week_number":35,"month":8},"sort":[1472601600000]},{"_index":"daily_temperature","_type":"_doc","_id":"gkunPnQBWtRdb_i9z57x","_score":null,"_source":{"station_id":"c24m124e03","date":"01-09-2016","t_min":16.2,"t_max":27.4,"t_avg":21.8,"week_number":35,"month":9},"sort":[1472688000000]},{"_index":"daily_temperature","_type":"_doc","_id":"gUunPnQBWtRdb_i9z57x","_score":null,"_source":{"station_id":"c24m124e03","date":"02-09-2016","t_min":14.8,"t_max":31.8,"t_avg":23.3,"week_number":36,"month":9},"sort":[1472774400000]},{"_index":"daily_temperature","_type":"_doc","_id":"gEunPnQBWtRdb_i9z57x","_score":null,"_source":{"station_id":"c24m124e03","date":"03-09-2016","t_min":16.8,"t_max":33.1,"t_avg":24.9,"week_number":36,"month":9},"sort":[1472860800000]},{"_index":"daily_temperature","_type":"_doc","_id":"f0unPnQBWtRdb_i9z57w","_score":null,"_source":{"station_id":"c24m124e03","date":"04-09-2016","t_min":17.7,"t_max":35.3,"t_avg":26.5,"week_number":36,"month":9},"sort":[1472947200000]},{"_index":"daily_temperature","_type":"_doc","_id":"fkunPnQBWtRdb_i9z57w","_score":null,"_source":{"station_id":"c24m124e03","date":"05-09-2016","t_min":20.8,"t_max":37.9,"t_avg":29.4,"week_number":36,"month":9},"sort":[1473033600000]},{"_index":"daily_temperature","_type":"_doc","_id":"fUunPnQBWtRdb_i9z57w","_score":null,"_source":{"station_id":"c24m124e03","date":"06-09-2016","t_min":19.8,"t_max":34.4,"t_avg":27.1,"week_number":36,"month":9},"sort":[1473120000000]},{"_index":"daily_temperature","_type":"_doc","_id":"fEunPnQBWtRdb_i9z57v","_score":null,"_source":{"station_id":"c24m124e03","date":"07-09-2016","t_min":17.4,"t_max":32.6,"t_avg":25,"week_number":36,"month":9},"sort":[1473206400000]},{"_index":"daily_temperature","_type":"_doc","_id":"e0unPnQBWtRdb_i9z57t","_score":null,"_source":{"station_id":"c24m124e03","date":"08-09-2016","t_min":16.4,"t_max":29.6,"t_avg":23,"week_number":36,"month":9},"sort":[1473292800000]},{"_index":"daily_temperature","_type":"_doc","_id":"ekunPnQBWtRdb_i9z57r","_score":null,"_source":{"station_id":"c24m124e03","date":"09-09-2016","t_min":16.7,"t_max":30.2,"t_avg":23.4,"week_number":37,"month":9},"sort":[1473379200000]},{"_index":"daily_temperature","_type":"_doc","_id":"eUunPnQBWtRdb_i9z57p","_score":null,"_source":{"station_id":"c24m124e03","date":"10-09-2016","t_min":17.2,"t_max":28,"t_avg":22.6,"week_number":37,"month":9},"sort":[1473465600000]},{"_index":"daily_temperature","_type":"_doc","_id":"eEunPnQBWtRdb_i9z57p","_score":null,"_source":{"station_id":"c24m124e03","date":"11-09-2016","t_min":17.1,"t_max":29.1,"t_avg":23.1,"week_number":37,"month":9},"sort":[1473552000000]},{"_index":"daily_temperature","_type":"_doc","_id":"d0unPnQBWtRdb_i9z57o","_score":null,"_source":{"station_id":"c24m124e03","date":"12-09-2016","t_min":15.6,"t_max":29.9,"t_avg":22.8,"week_number":37,"month":9},"sort":[1473638400000]},{"_index":"daily_temperature","_type":"_doc","_id":"dkunPnQBWtRdb_i9z57m","_score":null,"_source":{"station_id":"c24m124e03","date":"13-09-2016","t_min":15.4,"t_max":27,"t_avg":21.2,"week_number":37,"month":9},"sort":[1473724800000]},{"_index":"daily_temperature","_type":"_doc","_id":"dUunPnQBWtRdb_i9z57m","_score":null,"_source":{"station_id":"c24m124e03","date":"14-09-2016","t_min":13.3,"t_max":20.7,"t_avg":17,"week_number":37,"month":9},"sort":[1473811200000]},{"_index":"daily_temperature","_type":"_doc","_id":"dEunPnQBWtRdb_i9z57l","_score":null,"_source":{"station_id":"c24m124e03","date":"15-09-2016","t_min":9.2,"t_max":21.7,"t_avg":15.4,"week_number":37,"month":9},"sort":[1473897600000]},{"_index":"daily_temperature","_type":"_doc","_id":"c0unPnQBWtRdb_i9z57l","_score":null,"_source":{"station_id":"c24m124e03","date":"16-09-2016","t_min":12.8,"t_max":25.1,"t_avg":18.9,"week_number":38,"month":9},"sort":[1473984000000]},{"_index":"daily_temperature","_type":"_doc","_id":"ckunPnQBWtRdb_i9z57k","_score":null,"_source":{"station_id":"c24m124e03","date":"17-09-2016","t_min":11.1,"t_max":25.6,"t_avg":18.4,"week_number":38,"month":9},"sort":[1474070400000]},{"_index":"daily_temperature","_type":"_doc","_id":"cUunPnQBWtRdb_i9z57k","_score":null,"_source":{"station_id":"c24m124e03","date":"18-09-2016","t_min":11.6,"t_max":24.1,"t_avg":17.9,"week_number":38,"month":9},"sort":[1474156800000]},{"_index":"daily_temperature","_type":"_doc","_id":"cEunPnQBWtRdb_i9z57k","_score":null,"_source":{"station_id":"c24m124e03","date":"19-09-2016","t_min":10.2,"t_max":26.3,"t_avg":18.2,"week_number":38,"month":9},"sort":[1474243200000]},{"_index":"daily_temperature","_type":"_doc","_id":"0kunPnQBWtRdb_i9zp35","_score":null,"_source":{"station_id":"c24m124e03","date":"20-09-2016","t_min":13.6,"t_max":24.9,"t_avg":19.2,"week_number":38,"month":9},"sort":[1474329600000]},{"_index":"daily_temperature","_type":"_doc","_id":"0UunPnQBWtRdb_i9zp34","_score":null,"_source":{"station_id":"c24m124e03","date":"21-09-2016","t_min":13.3,"t_max":27.9,"t_avg":20.6,"week_number":38,"month":9},"sort":[1474416000000]},{"_index":"daily_temperature","_type":"_doc","_id":"0EunPnQBWtRdb_i9zp34","_score":null,"_source":{"station_id":"c24m124e03","date":"22-09-2016","t_min":12.1,"t_max":26.1,"t_avg":19.1,"week_number":38,"month":9},"sort":[1474502400000]},{"_index":"daily_temperature","_type":"_doc","_id":"z0unPnQBWtRdb_i9zp31","_score":null,"_source":{"station_id":"c24m124e03","date":"23-09-2016","t_min":13.5,"t_max":26.6,"t_avg":20.1,"week_number":39,"month":9},"sort":[1474588800000]},{"_index":"daily_temperature","_type":"_doc","_id":"zkunPnQBWtRdb_i9zp30","_score":null,"_source":{"station_id":"c24m124e03","date":"24-09-2016","t_min":11.9,"t_max":25.7,"t_avg":18.8,"week_number":39,"month":9},"sort":[1474675200000]},{"_index":"daily_temperature","_type":"_doc","_id":"P0unPnQBWtRdb_i9z55-","_score":null,"_source":{"station_id":"c24m124e03","date":"25-09-2016","t_min":14.5,"t_max":26.4,"t_avg":20.4,"week_number":39,"month":9},"sort":[1474761600000]},{"_index":"daily_temperature","_type":"_doc","_id":"QEunPnQBWtRdb_i9z55-","_score":null,"_source":{"station_id":"c24m124e03","date":"26-09-2016","t_min":17,"t_max":23.5,"t_avg":20.2,"week_number":39,"month":9},"sort":[1474848000000]},{"_index":"daily_temperature","_type":"_doc","_id":"QUunPnQBWtRdb_i9z55-","_score":null,"_source":{"station_id":"c24m124e03","date":"27-09-2016","t_min":15.2,"t_max":24.2,"t_avg":19.7,"week_number":39,"month":9},"sort":[1474934400000]},{"_index":"daily_temperature","_type":"_doc","_id":"QkunPnQBWtRdb_i9z55_","_score":null,"_source":{"station_id":"c24m124e03","date":"28-09-2016","t_min":14.9,"t_max":19.2,"t_avg":17.1,"week_number":39,"month":9},"sort":[1475020800000]},{"_index":"daily_temperature","_type":"_doc","_id":"Q0unPnQBWtRdb_i9z55_","_score":null,"_source":{"station_id":"c24m124e03","date":"29-09-2016","t_min":13.8,"t_max":21.1,"t_avg":17.4,"week_number":39,"month":9},"sort":[1475107200000]},{"_index":"daily_temperature","_type":"_doc","_id":"REunPnQBWtRdb_i9z55_","_score":null,"_source":{"station_id":"c24m124e03","date":"30-09-2016","t_min":13.6,"t_max":21.9,"t_avg":17.8,"week_number":40,"month":9},"sort":[1475193600000]},{"_index":"daily_temperature","_type":"_doc","_id":"JEunPnQBWtRdb_i9ypqo","_score":null,"_source":{"station_id":"c24m124e03","date":"01-10-2016","t_min":12.8,"t_max":26.6,"t_avg":19.7,"week_number":40,"month":10},"sort":[1475280000000]},{"_index":"daily_temperature","_type":"_doc","_id":"LEunPnQBWtRdb_i9ypqw","_score":null,"_source":{"station_id":"c24m124e03","date":"02-10-2016","t_min":15.3,"t_max":27.3,"t_avg":21.3,"week_number":40,"month":10},"sort":[1475366400000]},{"_index":"daily_temperature","_type":"_doc","_id":"P0unPnQBWtRdb_i9ypq6","_score":null,"_source":{"station_id":"c24m124e03","date":"03-10-2016","t_min":14.9,"t_max":25,"t_avg":19.9,"week_number":40,"month":10},"sort":[1475452800000]},{"_index":"daily_temperature","_type":"_doc","_id":"KUunPnQBWtRdb_i9ypqp","_score":null,"_source":{"station_id":"c24m124e03","date":"04-10-2016","t_min":13.1,"t_max":28.1,"t_avg":20.6,"week_number":40,"month":10},"sort":[1475539200000]},{"_index":"daily_temperature","_type":"_doc","_id":"RUunPnQBWtRdb_i9ypq7","_score":null,"_source":{"station_id":"c24m124e03","date":"05-10-2016","t_min":16.3,"t_max":24.7,"t_avg":20.5,"week_number":40,"month":10},"sort":[1475625600000]},{"_index":"daily_temperature","_type":"_doc","_id":"9kunPnQBWtRdb_i9ypmb","_score":null,"_source":{"station_id":"c24m124e03","date":"06-10-2016","t_min":14.8,"t_max":28.5,"t_avg":21.6,"week_number":40,"month":10},"sort":[1475712000000]},{"_index":"daily_temperature","_type":"_doc","_id":"L0unPnQBWtRdb_i9ypqw","_score":null,"_source":{"station_id":"c24m124e03","date":"07-10-2016","t_min":14.9,"t_max":27.1,"t_avg":21,"week_number":41,"month":10},"sort":[1475798400000]},{"_index":"daily_temperature","_type":"_doc","_id":"30unPnQBWtRdb_i9ypmU","_score":null,"_source":{"station_id":"c24m124e03","date":"08-10-2016","t_min":13.5,"t_max":26.8,"t_avg":20.1,"week_number":41,"month":10},"sort":[1475884800000]},{"_index":"daily_temperature","_type":"_doc","_id":"QkunPnQBWtRdb_i9ypq6","_score":null,"_source":{"station_id":"c24m124e03","date":"09-10-2016","t_min":15.8,"t_max":21,"t_avg":18.4,"week_number":41,"month":10},"sort":[1475971200000]},{"_index":"daily_temperature","_type":"_doc","_id":"FEunPnQBWtRdb_i9ypqj","_score":null,"_source":{"station_id":"c24m124e03","date":"10-10-2016","t_min":15.2,"t_max":23.8,"t_avg":19.5,"week_number":41,"month":10},"sort":[1476057600000]},{"_index":"daily_temperature","_type":"_doc","_id":"HEunPnQBWtRdb_i9ypqk","_score":null,"_source":{"station_id":"c24m124e03","date":"11-10-2016","t_min":12.2,"t_max":25.6,"t_avg":18.9,"week_number":41,"month":10},"sort":[1476144000000]},{"_index":"daily_temperature","_type":"_doc","_id":"LUunPnQBWtRdb_i9ypqw","_score":null,"_source":{"station_id":"c24m124e03","date":"12-10-2016","t_min":14.2,"t_max":19.9,"t_avg":17.1,"week_number":41,"month":10},"sort":[1476230400000]},{"_index":"daily_temperature","_type":"_doc","_id":"AEunPnQBWtRdb_i9ypqd","_score":null,"_source":{"station_id":"c24m124e03","date":"13-10-2016","t_min":11.8,"t_max":16.2,"t_avg":14,"week_number":41,"month":10},"sort":[1476316800000]},{"_index":"daily_temperature","_type":"_doc","_id":"7EunPnQBWtRdb_i9ypmZ","_score":null,"_source":{"station_id":"c24m124e03","date":"14-10-2016","t_min":11.6,"t_max":18.8,"t_avg":15.2,"week_number":42,"month":10},"sort":[1476403200000]},{"_index":"daily_temperature","_type":"_doc","_id":"zUunPnQBWtRdb_i9ypmO","_score":null,"_source":{"station_id":"c24m124e03","date":"15-10-2016","t_min":8.5,"t_max":20.9,"t_avg":14.7,"week_number":42,"month":10},"sort":[1476489600000]},{"_index":"daily_temperature","_type":"_doc","_id":"10unPnQBWtRdb_i9ypmR","_score":null,"_source":{"station_id":"c24m124e03","date":"16-10-2016","t_min":9.1,"t_max":21.9,"t_avg":15.5,"week_number":42,"month":10},"sort":[1476576000000]},{"_index":"daily_temperature","_type":"_doc","_id":"PEunPnQBWtRdb_i9ypqy","_score":null,"_source":{"station_id":"c24m124e03","date":"17-10-2016","t_min":13.4,"t_max":25.3,"t_avg":19.4,"week_number":42,"month":10},"sort":[1476662400000]},{"_index":"daily_temperature","_type":"_doc","_id":"0UunPnQBWtRdb_i9ypmQ","_score":null,"_source":{"station_id":"c24m124e03","date":"18-10-2016","t_min":14.5,"t_max":17.3,"t_avg":15.9,"week_number":42,"month":10},"sort":[1476748800000]},{"_index":"daily_temperature","_type":"_doc","_id":"90unPnQBWtRdb_i9ypmb","_score":null,"_source":{"station_id":"c24m124e03","date":"19-10-2016","t_min":13.8,"t_max":18.9,"t_avg":16.4,"week_number":42,"month":10},"sort":[1476835200000]},{"_index":"daily_temperature","_type":"_doc","_id":"MEunPnQBWtRdb_i9ypqw","_score":null,"_source":{"station_id":"c24m124e03","date":"20-10-2016","t_min":12.4,"t_max":17.9,"t_avg":15.2,"week_number":42,"month":10},"sort":[1476921600000]},{"_index":"daily_temperature","_type":"_doc","_id":"B0unPnQBWtRdb_i9ypqe","_score":null,"_source":{"station_id":"c24m124e03","date":"21-10-2016","t_min":11.4,"t_max":14.5,"t_avg":12.9,"week_number":43,"month":10},"sort":[1477008000000]},{"_index":"daily_temperature","_type":"_doc","_id":"M0unPnQBWtRdb_i9ypqx","_score":null,"_source":{"station_id":"c24m124e03","date":"22-10-2016","t_min":13.3,"t_max":19.8,"t_avg":16.6,"week_number":43,"month":10},"sort":[1477094400000]},{"_index":"daily_temperature","_type":"_doc","_id":"6UunPnQBWtRdb_i9ypmX","_score":null,"_source":{"station_id":"c24m124e03","date":"23-10-2016","t_min":13.2,"t_max":21.3,"t_avg":17.2,"week_number":43,"month":10},"sort":[1477180800000]},{"_index":"daily_temperature","_type":"_doc","_id":"KEunPnQBWtRdb_i9ypqp","_score":null,"_source":{"station_id":"c24m124e03","date":"24-10-2016","t_min":12.9,"t_max":20.9,"t_avg":16.9,"week_number":43,"month":10},"sort":[1477267200000]},{"_index":"daily_temperature","_type":"_doc","_id":"ykunPnQBWtRdb_i9ypmG","_score":null,"_source":{"station_id":"c24m124e03","date":"25-10-2016","t_min":14.8,"t_max":17.9,"t_avg":16.4,"week_number":43,"month":10},"sort":[1477353600000]},{"_index":"daily_temperature","_type":"_doc","_id":"GUunPnQBWtRdb_i9ypqk","_score":null,"_source":{"station_id":"c24m124e03","date":"26-10-2016","t_min":14.8,"t_max":22.5,"t_avg":18.6,"week_number":43,"month":10},"sort":[1477440000000]},{"_index":"daily_temperature","_type":"_doc","_id":"PkunPnQBWtRdb_i9ypqy","_score":null,"_source":{"station_id":"c24m124e03","date":"27-10-2016","t_min":13.6,"t_max":23.2,"t_avg":18.4,"week_number":43,"month":10},"sort":[1477526400000]},{"_index":"daily_temperature","_type":"_doc","_id":"J0unPnQBWtRdb_i9ypqp","_score":null,"_source":{"station_id":"c24m124e03","date":"28-10-2016","t_min":11.8,"t_max":20.8,"t_avg":16.3,"week_number":44,"month":10},"sort":[1477612800000]},{"_index":"daily_temperature","_type":"_doc","_id":"F0unPnQBWtRdb_i9ypqk","_score":null,"_source":{"station_id":"c24m124e03","date":"29-10-2016","t_min":6.5,"t_max":22.6,"t_avg":14.6,"week_number":44,"month":10},"sort":[1477699200000]},{"_index":"daily_temperature","_type":"_doc","_id":"_kunPnQBWtRdb_i9ypmd","_score":null,"_source":{"station_id":"c24m124e03","date":"30-10-2016","t_min":9,"t_max":24,"t_avg":16.5,"week_number":44,"month":10},"sort":[1477785600000]},{"_index":"daily_temperature","_type":"_doc","_id":"0kunPnQBWtRdb_i9ypmQ","_score":null,"_source":{"station_id":"c24m124e03","date":"31-10-2016","t_min":8.9,"t_max":19.7,"t_avg":14.3,"week_number":44,"month":10},"sort":[1477872000000]},{"_index":"daily_temperature","_type":"_doc","_id":"pUunPnQBWtRdb_i9ypls","_score":null,"_source":{"station_id":"c24m124e03","date":"01-11-2016","t_min":9.3,"t_max":19.4,"t_avg":14.3,"week_number":44,"month":11},"sort":[1477958400000]},{"_index":"daily_temperature","_type":"_doc","_id":"o0unPnQBWtRdb_i9ypls","_score":null,"_source":{"station_id":"c24m124e03","date":"02-11-2016","t_min":7.9,"t_max":24.4,"t_avg":16.1,"week_number":44,"month":11},"sort":[1478044800000]},{"_index":"daily_temperature","_type":"_doc","_id":"s0unPnQBWtRdb_i9ypmE","_score":null,"_source":{"station_id":"c24m124e03","date":"03-11-2016","t_min":11.5,"t_max":23.3,"t_avg":17.4,"week_number":44,"month":11},"sort":[1478131200000]},{"_index":"daily_temperature","_type":"_doc","_id":"rUunPnQBWtRdb_i9ypmD","_score":null,"_source":{"station_id":"c24m124e03","date":"04-11-2016","t_min":13.1,"t_max":21.1,"t_avg":17.1,"week_number":45,"month":11},"sort":[1478217600000]},{"_index":"daily_temperature","_type":"_doc","_id":"yEunPnQBWtRdb_i9ypmG","_score":null,"_source":{"station_id":"c24m124e03","date":"05-11-2016","t_min":13.7,"t_max":20.6,"t_avg":17.1,"week_number":45,"month":11},"sort":[1478304000000]},{"_index":"daily_temperature","_type":"_doc","_id":"r0unPnQBWtRdb_i9ypmE","_score":null,"_source":{"station_id":"c24m124e03","date":"06-11-2016","t_min":6.1,"t_max":13.7,"t_avg":9.9,"week_number":45,"month":11},"sort":[1478390400000]},{"_index":"daily_temperature","_type":"_doc","_id":"q0unPnQBWtRdb_i9ypmD","_score":null,"_source":{"station_id":"c24m124e03","date":"07-11-2016","t_min":3.1,"t_max":12.1,"t_avg":7.6,"week_number":45,"month":11},"sort":[1478476800000]},{"_index":"daily_temperature","_type":"_doc","_id":"qkunPnQBWtRdb_i9ypmD","_score":null,"_source":{"station_id":"c24m124e03","date":"08-11-2016","t_min":2.8,"t_max":11.6,"t_avg":7.2,"week_number":45,"month":11},"sort":[1478563200000]},{"_index":"daily_temperature","_type":"_doc","_id":"rkunPnQBWtRdb_i9ypmE","_score":null,"_source":{"station_id":"c24m124e03","date":"09-11-2016","t_min":6.9,"t_max":12.2,"t_avg":9.6,"week_number":45,"month":11},"sort":[1478649600000]},{"_index":"daily_temperature","_type":"_doc","_id":"qEunPnQBWtRdb_i9ypmD","_score":null,"_source":{"station_id":"c24m124e03","date":"10-11-2016","t_min":5.3,"t_max":15.5,"t_avg":10.4,"week_number":45,"month":11},"sort":[1478736000000]},{"_index":"daily_temperature","_type":"_doc","_id":"vUunPnQBWtRdb_i9ypmF","_score":null,"_source":{"station_id":"c24m124e03","date":"11-11-2016","t_min":2.6,"t_max":18.7,"t_avg":10.7,"week_number":46,"month":11},"sort":[1478822400000]},{"_index":"daily_temperature","_type":"_doc","_id":"REunPnQBWtRdb_i9ypq7","_score":null,"_source":{"station_id":"c24m124e03","date":"12-11-2016","t_min":4.1,"t_max":17.8,"t_avg":10.9,"week_number":46,"month":11},"sort":[1478908800000]},{"_index":"daily_temperature","_type":"_doc","_id":"_EunPnQBWtRdb_i9ypmc","_score":null,"_source":{"station_id":"c24m124e03","date":"13-11-2016","t_min":7,"t_max":19,"t_avg":13,"week_number":46,"month":11},"sort":[1478995200000]},{"_index":"daily_temperature","_type":"_doc","_id":"IkunPnQBWtRdb_i9ypqo","_score":null,"_source":{"station_id":"c24m124e03","date":"14-11-2016","t_min":6.3,"t_max":12.6,"t_avg":9.4,"week_number":46,"month":11},"sort":[1479081600000]},{"_index":"daily_temperature","_type":"_doc","_id":"BkunPnQBWtRdb_i9ypqe","_score":null,"_source":{"station_id":"c24m124e03","date":"15-11-2016","t_min":7.1,"t_max":11.5,"t_avg":9.3,"week_number":46,"month":11},"sort":[1479168000000]},{"_index":"daily_temperature","_type":"_doc","_id":"50unPnQBWtRdb_i9ypmW","_score":null,"_source":{"station_id":"c24m124e03","date":"16-11-2016","t_min":4.6,"t_max":12.2,"t_avg":8.4,"week_number":46,"month":11},"sort":[1479254400000]},{"_index":"daily_temperature","_type":"_doc","_id":"z0unPnQBWtRdb_i9ypmO","_score":null,"_source":{"station_id":"c24m124e03","date":"17-11-2016","t_min":3.5,"t_max":17.9,"t_avg":10.7,"week_number":46,"month":11},"sort":[1479340800000]},{"_index":"daily_temperature","_type":"_doc","_id":"BEunPnQBWtRdb_i9ypqe","_score":null,"_source":{"station_id":"c24m124e03","date":"18-11-2016","t_min":4.1,"t_max":19,"t_avg":11.6,"week_number":47,"month":11},"sort":[1479427200000]},{"_index":"daily_temperature","_type":"_doc","_id":"_0unPnQBWtRdb_i9ypmd","_score":null,"_source":{"station_id":"c24m124e03","date":"19-11-2016","t_min":9.1,"t_max":17.5,"t_avg":13.3,"week_number":47,"month":11},"sort":[1479513600000]},{"_index":"daily_temperature","_type":"_doc","_id":"FUunPnQBWtRdb_i9ypqk","_score":null,"_source":{"station_id":"c24m124e03","date":"20-11-2016","t_min":5.6,"t_max":16.2,"t_avg":10.9,"week_number":47,"month":11},"sort":[1479600000000]},{"_index":"daily_temperature","_type":"_doc","_id":"-0unPnQBWtRdb_i9ypmc","_score":null,"_source":{"station_id":"c24m124e03","date":"21-11-2016","t_min":12.3,"t_max":16.2,"t_avg":14.2,"week_number":47,"month":11},"sort":[1479686400000]},{"_index":"daily_temperature","_type":"_doc","_id":"5kunPnQBWtRdb_i9ypmW","_score":null,"_source":{"station_id":"c24m124e03","date":"22-11-2016","t_min":7.5,"t_max":12.7,"t_avg":10.1,"week_number":47,"month":11},"sort":[1479772800000]},{"_index":"daily_temperature","_type":"_doc","_id":"20unPnQBWtRdb_i9ypmT","_score":null,"_source":{"station_id":"c24m124e03","date":"23-11-2016","t_min":6.4,"t_max":9.4,"t_avg":7.9,"week_number":47,"month":11},"sort":[1479859200000]},{"_index":"daily_temperature","_type":"_doc","_id":"4UunPnQBWtRdb_i9ypmU","_score":null,"_source":{"station_id":"c24m124e03","date":"24-11-2016","t_min":3.5,"t_max":10.6,"t_avg":7,"week_number":47,"month":11},"sort":[1479945600000]},{"_index":"daily_temperature","_type":"_doc","_id":"0EunPnQBWtRdb_i9ypmO","_score":null,"_source":{"station_id":"c24m124e03","date":"25-11-2016","t_min":2.4,"t_max":11.4,"t_avg":6.9,"week_number":48,"month":11},"sort":[1480032000000]},{"_index":"daily_temperature","_type":"_doc","_id":"_UunPnQBWtRdb_i9ypmc","_score":null,"_source":{"station_id":"c24m124e03","date":"26-11-2016","t_min":5.1,"t_max":9.9,"t_avg":7.5,"week_number":48,"month":11},"sort":[1480118400000]},{"_index":"daily_temperature","_type":"_doc","_id":"70unPnQBWtRdb_i9ypmZ","_score":null,"_source":{"station_id":"c24m124e03","date":"27-11-2016","t_min":5.3,"t_max":10.2,"t_avg":7.8,"week_number":48,"month":11},"sort":[1480204800000]},{"_index":"daily_temperature","_type":"_doc","_id":"2EunPnQBWtRdb_i9ypmR","_score":null,"_source":{"station_id":"c24m124e03","date":"28-11-2016","t_min":7.1,"t_max":9.7,"t_avg":8.4,"week_number":48,"month":11},"sort":[1480291200000]},{"_index":"daily_temperature","_type":"_doc","_id":"DEunPnQBWtRdb_i9ypqg","_score":null,"_source":{"station_id":"c24m124e03","date":"29-11-2016","t_min":7.8,"t_max":9.4,"t_avg":8.6,"week_number":48,"month":11},"sort":[1480377600000]},{"_index":"daily_temperature","_type":"_doc","_id":"4kunPnQBWtRdb_i9ypmU","_score":null,"_source":{"station_id":"c24m124e03","date":"30-11-2016","t_min":8.7,"t_max":11,"t_avg":9.8,"week_number":48,"month":11},"sort":[1480464000000]},{"_index":"daily_temperature","_type":"_doc","_id":"CkunPnQBWtRdb_i9zJx7","_score":null,"_source":{"station_id":"c24m124e03","date":"01-12-2016","t_min":6.7,"t_max":10.6,"t_avg":8.7,"week_number":48,"month":12},"sort":[1480550400000]},{"_index":"daily_temperature","_type":"_doc","_id":"H0unPnQBWtRdb_i9zJyB","_score":null,"_source":{"station_id":"c24m124e03","date":"02-12-2016","t_min":4.8,"t_max":15,"t_avg":9.9,"week_number":49,"month":12},"sort":[1480636800000]},{"_index":"daily_temperature","_type":"_doc","_id":"FkunPnQBWtRdb_i9zJx-","_score":null,"_source":{"station_id":"c24m124e03","date":"03-12-2016","t_min":5.4,"t_max":12.8,"t_avg":9.1,"week_number":49,"month":12},"sort":[1480723200000]},{"_index":"daily_temperature","_type":"_doc","_id":"80unPnQBWtRdb_i9zJtz","_score":null,"_source":{"station_id":"c24m124e03","date":"04-12-2016","t_min":8.9,"t_max":11.4,"t_avg":10.2,"week_number":49,"month":12},"sort":[1480809600000]},{"_index":"daily_temperature","_type":"_doc","_id":"2UunPnQBWtRdb_i9zJtp","_score":null,"_source":{"station_id":"c24m124e03","date":"05-12-2016","t_min":10.6,"t_max":12.4,"t_avg":11.5,"week_number":49,"month":12},"sort":[1480896000000]},{"_index":"daily_temperature","_type":"_doc","_id":"AEunPnQBWtRdb_i9zJx3","_score":null,"_source":{"station_id":"c24m124e03","date":"06-12-2016","t_min":8.7,"t_max":11.3,"t_avg":10,"week_number":49,"month":12},"sort":[1480982400000]},{"_index":"daily_temperature","_type":"_doc","_id":"5EunPnQBWtRdb_i9zJtv","_score":null,"_source":{"station_id":"c24m124e03","date":"07-12-2016","t_min":4.7,"t_max":12.7,"t_avg":8.7,"week_number":49,"month":12},"sort":[1481068800000]},{"_index":"daily_temperature","_type":"_doc","_id":"7UunPnQBWtRdb_i9zJty","_score":null,"_source":{"station_id":"c24m124e03","date":"08-12-2016","t_min":7.7,"t_max":9.7,"t_avg":8.7,"week_number":49,"month":12},"sort":[1481155200000]},{"_index":"daily_temperature","_type":"_doc","_id":"8UunPnQBWtRdb_i9zJtz","_score":null,"_source":{"station_id":"c24m124e03","date":"09-12-2016","t_min":8.4,"t_max":12.4,"t_avg":10.4,"week_number":50,"month":12},"sort":[1481241600000]},{"_index":"daily_temperature","_type":"_doc","_id":"2EunPnQBWtRdb_i9zJtp","_score":null,"_source":{"station_id":"c24m124e03","date":"10-12-2016","t_min":7.1,"t_max":13.8,"t_avg":10.4,"week_number":50,"month":12},"sort":[1481328000000]},{"_index":"daily_temperature","_type":"_doc","_id":"DUunPnQBWtRdb_i9zJx7","_score":null,"_source":{"station_id":"c24m124e03","date":"11-12-2016","t_min":4.1,"t_max":15.4,"t_avg":9.8,"week_number":50,"month":12},"sort":[1481414400000]},{"_index":"daily_temperature","_type":"_doc","_id":"40unPnQBWtRdb_i9zJtv","_score":null,"_source":{"station_id":"c24m124e03","date":"12-12-2016","t_min":3.5,"t_max":13.8,"t_avg":8.7,"week_number":50,"month":12},"sort":[1481500800000]},{"_index":"daily_temperature","_type":"_doc","_id":"AUunPnQBWtRdb_i9zJx3","_score":null,"_source":{"station_id":"c24m124e03","date":"13-12-2016","t_min":3,"t_max":12.4,"t_avg":7.7,"week_number":50,"month":12},"sort":[1481587200000]},{"_index":"daily_temperature","_type":"_doc","_id":"-0unPnQBWtRdb_i9zJt2","_score":null,"_source":{"station_id":"c24m124e03","date":"14-12-2016","t_min":3.7,"t_max":11.9,"t_avg":7.8,"week_number":50,"month":12},"sort":[1481673600000]},{"_index":"daily_temperature","_type":"_doc","_id":"vEunPnQBWtRdb_i9zJtc","_score":null,"_source":{"station_id":"c24m124e03","date":"15-12-2016","t_min":4.7,"t_max":8,"t_avg":6.3,"week_number":50,"month":12},"sort":[1481760000000]},{"_index":"daily_temperature","_type":"_doc","_id":"3EunPnQBWtRdb_i9zJtu","_score":null,"_source":{"station_id":"c24m124e03","date":"16-12-2016","t_min":6.9,"t_max":9.3,"t_avg":8.1,"week_number":51,"month":12},"sort":[1481846400000]},{"_index":"daily_temperature","_type":"_doc","_id":"ykunPnQBWtRdb_i9zJti","_score":null,"_source":{"station_id":"c24m124e03","date":"17-12-2016","t_min":7.6,"t_max":9.9,"t_avg":8.8,"week_number":51,"month":12},"sort":[1481932800000]},{"_index":"daily_temperature","_type":"_doc","_id":"uUunPnQBWtRdb_i9zJtX","_score":null,"_source":{"station_id":"c24m124e03","date":"18-12-2016","t_min":6.7,"t_max":8.5,"t_avg":7.6,"week_number":51,"month":12},"sort":[1482019200000]},{"_index":"daily_temperature","_type":"_doc","_id":"w0unPnQBWtRdb_i9zJte","_score":null,"_source":{"station_id":"c24m124e03","date":"19-12-2016","t_min":5.2,"t_max":7.7,"t_avg":6.5,"week_number":51,"month":12},"sort":[1482105600000]},{"_index":"daily_temperature","_type":"_doc","_id":"O0unPnQBWtRdb_i9zJyV","_score":null,"_source":{"station_id":"c24m124e03","date":"20-12-2016","t_min":4.3,"t_max":9.9,"t_avg":7.1,"week_number":51,"month":12},"sort":[1482192000000]},{"_index":"daily_temperature","_type":"_doc","_id":"SEunPnQBWtRdb_i9zJyZ","_score":null,"_source":{"station_id":"c24m124e03","date":"21-12-2016","t_min":1.6,"t_max":10.3,"t_avg":6,"week_number":51,"month":12},"sort":[1482278400000]},{"_index":"daily_temperature","_type":"_doc","_id":"P0unPnQBWtRdb_i9zJyX","_score":null,"_source":{"station_id":"c24m124e03","date":"22-12-2016","t_min":3.1,"t_max":13.1,"t_avg":8.1,"week_number":51,"month":12},"sort":[1482364800000]},{"_index":"daily_temperature","_type":"_doc","_id":"SUunPnQBWtRdb_i9zJyZ","_score":null,"_source":{"station_id":"c24m124e03","date":"23-12-2016","t_min":2.9,"t_max":14.2,"t_avg":8.6,"week_number":52,"month":12},"sort":[1482451200000]},{"_index":"daily_temperature","_type":"_doc","_id":"TEunPnQBWtRdb_i9zJya","_score":null,"_source":{"station_id":"c24m124e03","date":"24-12-2016","t_min":4.1,"t_max":14.4,"t_avg":9.2,"week_number":52,"month":12},"sort":[1482537600000]},{"_index":"daily_temperature","_type":"_doc","_id":"LkunPnQBWtRdb_i9zJyQ","_score":null,"_source":{"station_id":"c24m124e03","date":"25-12-2016","t_min":2.5,"t_max":14.4,"t_avg":8.4,"week_number":52,"month":12},"sort":[1482624000000]},{"_index":"daily_temperature","_type":"_doc","_id":"OUunPnQBWtRdb_i9zJyV","_score":null,"_source":{"station_id":"c24m124e03","date":"26-12-2016","t_min":4.3,"t_max":18.1,"t_avg":11.2,"week_number":52,"month":12},"sort":[1482710400000]},{"_index":"daily_temperature","_type":"_doc","_id":"QkunPnQBWtRdb_i9zJyY","_score":null,"_source":{"station_id":"c24m124e03","date":"27-12-2016","t_min":4.7,"t_max":13.2,"t_avg":8.9,"week_number":52,"month":12},"sort":[1482796800000]},{"_index":"daily_temperature","_type":"_doc","_id":"PUunPnQBWtRdb_i9zJyX","_score":null,"_source":{"station_id":"c24m124e03","date":"28-12-2016","t_min":5,"t_max":8.1,"t_avg":6.5,"week_number":52,"month":12},"sort":[1482883200000]},{"_index":"daily_temperature","_type":"_doc","_id":"XUunPnQBWtRdb_i9zJyf","_score":null,"_source":{"station_id":"c24m124e03","date":"29-12-2016","t_min":2.7,"t_max":13.7,"t_avg":8.2,"week_number":52,"month":12},"sort":[1482969600000]},{"_index":"daily_temperature","_type":"_doc","_id":"K0unPnQBWtRdb_i9zJyQ","_score":null,"_source":{"station_id":"c24m124e03","date":"30-12-2016","t_min":3.9,"t_max":10.6,"t_avg":7.2,"week_number":53,"month":12},"sort":[1483056000000]},{"_index":"daily_temperature","_type":"_doc","_id":"NEunPnQBWtRdb_i9zJyU","_score":null,"_source":{"station_id":"c24m124e03","date":"31-12-2016","t_min":2.1,"t_max":9.1,"t_avg":5.6,"week_number":53,"month":12},"sort":[1483142400000]},{"_index":"daily_temperature","_type":"_doc","_id":"kUunPnQBWtRdb_i9zJzK","_score":null,"_source":{"station_id":"c24m124e03","date":"01-01-2017","t_min":1.8,"t_max":10.7,"t_avg":6.2,"week_number":1,"month":1},"sort":[1483228800000]}]}}